Workbook

Sheet Guia
A1: Sistema de Leads — AniCare (Limpieza) — Panamá
A2: Zonas prioritarias: Costa del Este · Santa María · Versalles PH1 · Reserva de Versalles · Versalles PH2
A4: CÓMO FUNCIONA ESTE ARCHIVO
A5: 1. Ve a la pestaña 'Leads' y llena las columnas amarillas (esas son las que editas a mano). Las demás columnas son fórmulas automáticas: no las toques.
A6: 2. La columna 'Duplicado' te avisa en automático (SI/NO) si ya existe un negocio con el mismo nombre y misma zona.
A7: 3. La columna 'Correo válido' revisa que el correo tenga formato correcto (usuario@dominio.com). No confirma que el correo exista de verdad, solo que la sintaxis esté bien.
A8: 4. La columna 'Teléfono válido' revisa que el número tenga formato panameño (8 dígitos, con o sin guion, o con +507).
A9: 5. La pestaña 'Resumen' se actualiza sola: leads por zona, por tipo de negocio y cuántos están verificados.
A11: DÓNDE CONSEGUIR LOS DATOS (gratis, sin programar)
A12: • Google Maps: busca "PH [nombre]", "oficinas Costa del Este", "clínica Santa María", etc. Anota nombre, dirección y teléfono de la ficha del negocio.
A13: • Sitio web del negocio (si tiene): entra a "Contacto" — ahí casi siempre está el correo real, más confiable que el de Google.
A14: • Administradoras de PH / Residenciales: muchos PH en Panamá los administra una empresa. Busca "administradora PH Versalles Panamá" — un solo contacto puede abrirte varios PH del sector.
... A26: Cuando tengas más presupuesto y volumen (miles de leads), vale la pena automatizar: un script que consulte Google Places API y OpenStreetMap para Panamá, cruce contra los sitios web de cada negocio, y aplique estas mismas reglas de validación y de-duplicado. Por ahora, con cientos de leads, este archivo manual-asistido es más rápido y sin costo.

Sheet Consultas
A1: Consultas de Búsqueda — Repite esto cada vez que quieras más leads
A2: Copia y pega estas frases en el chat con Claude (o en Google) para pedir más negocios de cada zona/tipo. Marca 'Hecho' cuando ya la uses.
A4: Zona | B4: Consulta sugerida | C4: Tipo de negocio | D4: Estado
A5: Costa del Este | B5: Busca más oficinas corporativas y edificios en Costa del Este Panamá con teléfono y correo de administración | C5: Oficina | D5: Pendiente
A6: Costa del Este / Santa María | B6: Busca clínicas, laboratorios y consultorios médicos en Santa María y Costa del Este Panamá con contacto | C6: Clínica | D6: Pendiente
A7: Versalles PH1 | B7: Busca administradoras o juntas directivas de PH en el sector Versalles (Torres de Versalles I) Panamá | C7: PH/Residencial | D7: Pendiente
A8: Versalles PH2 / Torres de Versalles II | B8: Busca administración o contacto de Torres de Versalles II en Juan Díaz Panamá | C8: PH/Residencial | D8: Pendiente
A9: Reserva de Versalles | B9: Busca administración del PH Reserva de Versalles ya construido (no oficina de ventas) en Panamá | C9: PH/Residencial | D9: Pendiente
A10: Ciudad de Panamá (general) | B10: Busca administradoras de PH en Panamá que gestionen varios edificios, con teléfono y correo | C10: Otro | D10: Pendiente
A11: Ciudad de Panamá (general) | B11: Busca hoteles boutique o de negocios en Ciudad de Panamá cerca de Costa del Este con teléfono | C11: Hotel | D11: Pendiente
A12: Costa del Este | B12: Busca clínicas dentales, spas o consultorios privados en Costa del Este Panamá con contacto | C12: Clínica | D12: Pendiente
A15: Cómo pedir la próxima tanda:
A16: Dile a Claude: "busca más leads de [tipo] en [zona] y cárgalos en el Excel", usando una fila de esta tabla como referencia. Claude buscará, verificará (reseñas, sitio web oficial) y los añadirá a la pestaña Leads sin borrar lo que ya tienes ni crear duplicados.

Sheet Leads
A1: ID | B1: Nombre del negocio | C1: Tipo | D1: Zona | E1: Dirección | F1: Teléfono | G1: Correo | H1: Sitio web | I1: Contacto (nombre) | J1: Visita AC | K1: Estado de verificación | L1: Duplicado | M1: Correo válido | N1: Teléfono válido | O1: Notas
A2: =IF(B2="","",ROW()-1) | B2: Clinilab Santa María | C2: Clínica | D2: Costa del Este | E2: Plaza Santa María (Chanis), Panamá | F2: +507 310-0680 | G2: info@clinilabpanama.com | H2: clinilabpanama.com | J2: No | K2: Sin verificar | L2: =IF(B2="","",IF(COUNTIFS($B$2:B2,B2,$D$2:D2,D2)>1,"SI","NO")) | M2: =IF(G2="","",IF(AND(ISNUMBER(SEARCH("@",G2)),ISNUMBER(SEARCH(".",G2,SEARCH("@",G2))),LEN(G2)-LEN(SUBSTITUTE(G2,"@",""))=1,MID(G2,SEARCH("@",G2)+1,1)<>".",RIGHT(G2,1)<>"."),"Válido","Revisar")) | N2: =IF(F2="","",IF(LEN(SUBSTITUTE(SUBSTITUTE(SUBSTITUTE(SUBSTITUTE(F2,"+507",""),"-",""),"(",""),")",""))=8,"Válido","Revisar")) | O2: Submercado Santa María, dentro del corredor de Costa del Este. Laboratorio clínico y medicina general. Horario: L-V 6am-7pm, Sáb 7am-3pm.
A3: =IF(B3="","",ROW()-1) | B3: Hospital Pacífica Salud Costa del Este | C3: Clínica | D3: Costa del Este | E3: Ave. Costa del Sol / Town Center, Costa del Este, Panamá | F3: (507) 204-8000 | G3: info@pacificasalud.com | H3: pacificasalud.com | J3: No | K3: Sin verificar | L3: =IF(B3="","",IF(COUNTIFS($B$2:B3,B3,$D$2:D3,D3)>1,"SI","NO")) | M3: =IF(G3="","",IF(AND(ISNUMBER(SEARCH("@",G3)),ISNUMBER(SEARCH(".",G3,SEARCH("@",G3))),LEN(G3)-LEN(SUBSTITUTE(G3,"@",""))=1,MID(G3,SEARCH("@",G3)+1,1)<>".",RIGHT(G3,1)<>"."),"Válido","Revisar")) | N3: =IF(F3="","",IF(LEN(SUBSTITUTE(SUBSTITUTE(SUBSTITUTE(SUBSTITUTE(F3,"+507",""),"-",""),"(",""),")",""))=8,"Válido","Revisar")) | O3: Hospital privado afiliado a Johns Hopkins Medicine International.
A4: =IF(B4="","",ROW()-1) | B4: Panama Diagnostic Center - Lab Costa del Este | C4: Clínica | D4: Costa del Este | E4: Plaza Ocean Drive, planta baja, junto a torre Aseguradora Ancón, Costa del Este | F4: WhatsApp 6285-7181 | H4: clinicapdc.com | J4: No | K4: Sin verificar | L4: =IF(B4="","",IF(COUNTIFS($B$2:B4,B4,$D$2:D4,D4)>1,"SI","NO")) | M4: =IF(G4="","",IF(AND(ISNUMBER(SEARCH("@",G4)),ISNUMBER(SEARCH(".",G4,SEARCH("@",G4))),LEN(G4)-LEN(SUBSTITUTE(G4,"@",""))=1,MID(G4,SEARCH("@",G4)+1,1)<>".",RIGHT(G4,1)<>"."),"Válido","Revisar")) | N4: =IF(F4="","",IF(LEN(SUBSTITUTE(SUBSTITUTE(SUBSTITUTE(SUBSTITUTE(F4,"+507",""),"-",""),"(",""),")",""))=8,"Válido","Revisar")) | O4: Medicina general, laboratorio y urgencias. Contacto principal es WhatsApp, no teléfono fijo.
A5: =IF(B5="","",ROW()-1) | B5: Plaza del Este | C5: Oficina | D5: Costa del Este | E5: Ave. Paseo del Mar, frente a Town Center, Costa del Este, Panamá | F5: +507 214-2376 | H5: plazadeleste.com | J5: No | K5: Sin verificar | L5: =IF(B5="","",IF(COUNTIFS($B$2:B5,B5,$D$2:D5,D5)>1,"SI","NO")) | M5: =IF(G5="","",IF(AND(ISNUMBER(SEARCH("@",G5)),ISNUMBER(SEARCH(".",G5,SEARCH("@",G5))),LEN(G5)-LEN(SUBSTITUTE(G5,"@",""))=1,MID(G5,SEARCH("@",G5)+1,1)<>".",RIGHT(G5,1)<>"."),"Válido","Revisar")) | N5: =IF(F5="","",IF(LEN(SUBSTITUTE(SUBSTITUTE(SUBSTITUTE(SUBSTITUTE(F5,"+507",""),"-",""),"(",""),")",""))=8,"Válido","Revisar")) | O5: Edificio corporativo de 20 pisos. El correo hallado en la búsqueda salió ilegible — confirmar vía sitio web.
A6: =IF(B6="","",ROW()-1) | B6: Santa María Plaza (administración) | C6: Oficina | D6: Costa del Este | E6: Entrada de Santa María Business District, salida Corredor Sur, Chanis/Costa del Este | F6: +507 6268-5993 | G6: administracion@santamariaplaza.com | H6: santamariaplaza.com | J6: No | K6: Sin verificar | L6: =IF(B6="","",IF(COUNTIFS($B$2:B6,B6,$D$2:D6,D6)>1,"SI","NO")) | M6: =IF(G6="","",IF(AND(ISNUMBER(SEARCH("@",G6)),ISNUMBER(SEARCH(".",G6,SEARCH("@",G6))),LEN(G6)-LEN(SUBSTITUTE(G6,"@",""))=1,MID(G6,SEARCH("@",G6)+1,1)<>".",RIGHT(G6,1)<>"."),"Válido","Revisar")) | N6: =IF(F6="","",IF(LEN(SUBSTITUTE(SUBSTITUTE(SUBSTITUTE(SUBSTITUTE(F6,"+507",""),"-",""),"(",""),")",""))=8,"Válido","Revisar")) | O6: Submercado Santa María, dentro del corredor de Costa del Este. 22 locales en planta baja y 21 en nivel 100. Buen punto para ofrecer limpieza a locales comerciales del área.
A7: =IF(B7="","",ROW()-1) | B7: The Santa Maria, A Luxury Collection Hotel & Golf Resort | C7: Hotel | D7: Costa del Este | E7: Calle 125 Este, Panamá | F7: +507 304-5555 | G7: ssolis@thesantamariahotel.com | H7: marriott.com | J7: No | K7: Sin verificar | L7: =IF(B7="","",IF(COUNTIFS($B$2:B7,B7,$D$2:D7,D7)>1,"SI","NO")) | M7: =IF(G7="","",IF(AND(ISNUMBER(SEARCH("@",G7)),ISNUMBER(SEARCH(".",G7,SEARCH("@",G7))),LEN(G7)-LEN(SUBSTITUTE(G7,"@",""))=1,MID(G7,SEARCH("@",G7)+1,1)<>".",RIGHT(G7,1)<>"."),"Válido","Revisar")) | N7: =IF(F7="","",IF(LEN(SUBSTITUTE(SUBSTITUTE(SUBSTITUTE(SUBSTITUTE(F7,"+507",""),"-",""),"(",""),")",""))=8,"Válido","Revisar")) | O7: Submercado Santa María, dentro del corredor de Costa del Este. También WhatsApp +507 6575-2289. Primer hotel Luxury Collection en Panamá, con campo de golf.
A8: =IF(B8="","",ROW()-1) | B8: Town Center Costa del Este (oficinas y academias) | C8: Oficina | D8: Costa del Este | E8: Av. Paseo del Mar, Costa del Este, Panamá | F8: 300-8696 | G8: mercadeo@towncenter.com.pa | H8: towncenter.com.pa | J8: No | K8: Sin verificar | L8: =IF(B8="","",IF(COUNTIFS($B$2:B8,B8,$D$2:D8,D8)>1,"SI","NO")) | M8: =IF(G8="","",IF(AND(ISNUMBER(SEARCH("@",G8)),ISNUMBER(SEARCH(".",G8,SEARCH("@",G8))),LEN(G8)-LEN(SUBSTITUTE(G8,"@",""))=1,MID(G8,SEARCH("@",G8)+1,1)<>".",RIGHT(G8,1)<>"."),"Válido","Revisar")) | N8: =IF(F8="","",IF(LEN(SUBSTITUTE(SUBSTITUTE(SUBSTITUTE(SUBSTITUTE(F8,"+507",""),"-",""),"(",""),")",""))=8,"Válido","Revisar")) | O8: Correo es de mercadeo del centro comercial; para el área de oficinas confirmar contacto específico.
A9: =IF(B9="","",ROW()-1) | B9: ADEMSA (administradora de PH) | C9: Otro | D9: Otra zona Ciudad de Panamá | E9: Punta Pacífica, PH Oceanía Business Plaza, Panamá | F9: 386-5040 / 6201-8936 | G9: info@admemp.com | H9: ademsa.com.pa | J9: No | K9: Sin verificar | L9: =IF(B9="","",IF(COUNTIFS($B$2:B9,B9,$D$2:D9,D9)>1,"SI","NO")) | M9: =IF(G9="","",IF(AND(ISNUMBER(SEARCH("@",G9)),ISNUMBER(SEARCH(".",G9,SEARCH("@",G9))),LEN(G9)-LEN(SUBSTITUTE(G9,"@",""))=1,MID(G9,SEARCH("@",G9)+1,1)<>".",RIGHT(G9,1)<>"."),"Válido","Revisar")) | N9: =IF(F9="","",IF(LEN(SUBSTITUTE(SUBSTITUTE(SUBSTITUTE(SUBSTITUTE(F9,"+507",""),"-",""),"(",""),")",""))=8,"Válido","Revisar")) | O9: Administradora que gestiona múltiples PH en la ciudad — buen punto de entrada para varios edificios a la vez.
A10: =IF(B10="","",ROW()-1) | B10: Easy Land (administración de PH) | C10: Otro | D10: Otra zona Ciudad de Panamá | E10: Panamá | F10: 339-6895 / 6813-4148 | H10: easylandpanama.com | J10: No | K10: Sin verificar | L10: =IF(B10="","",IF(COUNTIFS($B$2:B10,B10,$D$2:D10,D10)>1,"SI","NO")) | M10: =IF(G10="","",IF(AND(ISNUMBER(SEARCH("@",G10)),ISNUMBER(SEARCH(".",G10,SEARCH("@",G10))),LEN(G10)-LEN(SUBSTITUTE(G10,"@",""))=1,MID(G10,SEARCH("@",G10)+1,1)<>".",RIGHT(G10,1)<>"."),"Válido","Revisar")) | N10: =IF(F10="","",IF(LEN(SUBSTITUTE(SUBSTITUTE(SUBSTITUTE(SUBSTITUTE(F10,"+507",""),"-",""),"(",""),")",""))=8,"Válido","Revisar")) | O10: Administradora multi-PH.
A11: =IF(B11="","",ROW()-1) | B11: Hotel Sortis | C11: Hotel | D11: Otra zona Ciudad de Panamá | E11: Calle 56 y 57 Este, Obarrio, Bella Vista, Panamá | F11: (507) 398-8888 | H11: sortishotel.com | J11: No | K11: Sin verificar | L11: =IF(B11="","",IF(COUNTIFS($B$2:B11,B11,$D$2:D11,D11)>1,"SI","NO")) | M11: =IF(G11="","",IF(AND(ISNUMBER(SEARCH("@",G11)),ISNUMBER(SEARCH(".",G11,SEARCH("@",G11))),LEN(G11)-LEN(SUBSTITUTE(G11,"@",""))=1,MID(G11,SEARCH("@",G11)+1,1)<>".",RIGHT(G11,1)<>"."),"Válido","Revisar")) | N11: =IF(F11="","",IF(LEN(SUBSTITUTE(SUBSTITUTE(SUBSTITUTE(SUBSTITUTE(F11,"+507",""),"-",""),"(",""),")",""))=8,"Válido","Revisar")) | O11: Existencia confirmada: 779 reseñas en Google (8.5/10 'Muy bueno'). Confirmar correo por sitio web/recepción.
A12: =IF(B12="","",ROW()-1) | B12: Mardem Administración, S.A. | C12: Otro | D12: Otra zona Ciudad de Panamá | E12: Avenida Ernesto T. Lefevre, Panamá | F12: +507 6673-3363 | H12: mardemadministracion.com | J12: No | K12: Sin verificar | L12: =IF(B12="","",IF(COUNTIFS($B$2:B12,B12,$D$2:D12,D12)>1,"SI","NO")) | M12: =IF(G12="","",IF(AND(ISNUMBER(SEARCH("@",G12)),ISNUMBER(SEARCH(".",G12,SEARCH("@",G12))),LEN(G12)-LEN(SUBSTITUTE(G12,"@",""))=1,MID(G12,SEARCH("@",G12)+1,1)<>".",RIGHT(G12,1)<>"."),"Válido","Revisar")) | N12: =IF(F12="","",IF(LEN(SUBSTITUTE(SUBSTITUTE(SUBSTITUTE(SUBSTITUTE(F12,"+507",""),"-",""),"(",""),")",""))=8,"Válido","Revisar")) | O12: Administradora multi-PH (oficinas, residenciales, plazas comerciales). No se encontró correo público — usar formulario del sitio web.
A13: =IF(B13="","",ROW()-1) | B13: Tu Casa PH | C13: Otro | D13: Otra zona Ciudad de Panamá | E13: PH Plaza 2000, Calle 50, Marbella (al lado del hotel Riu), Oficina 14, Panamá | F13: +507 227-4333 | G13: info@tcadm.com | H13: tucasaph.com | J13: No | K13: Sin verificar | L13: =IF(B13="","",IF(COUNTIFS($B$2:B13,B13,$D$2:D13,D13)>1,"SI","NO")) | M13: =IF(G13="","",IF(AND(ISNUMBER(SEARCH("@",G13)),ISNUMBER(SEARCH(".",G13,SEARCH("@",G13))),LEN(G13)-LEN(SUBSTITUTE(G13,"@",""))=1,MID(G13,SEARCH("@",G13)+1,1)<>".",RIGHT(G13,1)<>"."),"Válido","Revisar")) | N13: =IF(F13="","",IF(LEN(SUBSTITUTE(SUBSTITUTE(SUBSTITUTE(SUBSTITUTE(F13,"+507",""),"-",""),"(",""),")",""))=8,"Válido","Revisar")) | O13: Administradora multi-PH con más de 15 años en el mercado panameño.
A14: =IF(B14="","",ROW()-1) | B14: Administra PTY (administradora, sirve Santa María Business District) | C14: Otro | D14: Costa del Este | E14: Santa María Business District, Costa del Este, Panamá | G14: contacto@administrapty.com | H14: administrapty.com | J14: No | K14: Sin verificar | L14: =IF(B14="","",IF(COUNTIFS($B$2:B14,B14,$D$2:D14,D14)>1,"SI","NO")) | M14: =IF(G14="","",IF(AND(ISNUMBER(SEARCH("@",G14)),ISNUMBER(SEARCH(".",G14,SEARCH("@",G14))),LEN(G14)-LEN(SUBSTITUTE(G14,"@",""))=1,MID(G14,SEARCH("@",G14)+1,1)<>".",RIGHT(G14,1)<>"."),"Válido","Revisar")) | N14: =IF(F14="","",IF(LEN(SUBSTITUTE(SUBSTITUTE(SUBSTITUTE(SUBSTITUTE(F14,"+507",""),"-",""),"(",""),")",""))=8,"Válido","Revisar")) | O14: Administradora que da servicio a propiedades del Santa María Business District — punto de entrada útil para varias torres del sector.
A15: =IF(B15="","",ROW()-1) | B15: PH Celeste (Santa María Golf & Country Club) | C15: PH/Residencial | D15: Costa del Este | E15: Santa María Golf & Country Club, Panamá | J15: No | K15: Sin verificar | L15: =IF(B15="","",IF(COUNTIFS($B$2:B15,B15,$D$2:D15,D15)>1,"SI","NO")) | M15: =IF(G15="","",IF(AND(ISNUMBER(SEARCH("@",G15)),ISNUMBER(SEARCH(".",G15,SEARCH("@",G15))),LEN(G15)-LEN(SUBSTITUTE(G15,"@",""))=1,MID(G15,SEARCH("@",G15)+1,1)<>".",RIGHT(G15,1)<>"."),"Válido","Revisar")) | N15: =IF(F15="","",IF(LEN(SUBSTITUTE(SUBSTITUTE(SUBSTITUTE(SUBSTITUTE(F15,"+507",""),"-",""),"(",""),")",""))=8,"Válido","Revisar")) | O15: Torre residencial de 42 niveles. Sin contacto directo público — verificar con Administra PTY o en portería.
A16: =IF(B16="","",ROW()-1) | B16: PH Corotú (Santa María Golf & Country Club) | C16: PH/Residencial | D16: Costa del Este | E16: Santa María Golf & Country Club, Panamá | J16: No | K16: Sin verificar | L16: =IF(B16="","",IF(COUNTIFS($B$2:B16,B16,$D$2:D16,D16)>1,"SI","NO")) | M16: =IF(G16="","",IF(AND(ISNUMBER(SEARCH("@",G16)),ISNUMBER(SEARCH(".",G16,SEARCH("@",G16))),LEN(G16)-LEN(SUBSTITUTE(G16,"@",""))=1,MID(G16,SEARCH("@",G16)+1,1)<>".",RIGHT(G16,1)<>"."),"Válido","Revisar")) | N16: =IF(F16="","",IF(LEN(SUBSTITUTE(SUBSTITUTE(SUBSTITUTE(SUBSTITUTE(F16,"+507",""),"-",""),"(",""),")",""))=8,"Válido","Revisar")) | O16: Torre de 47 niveles, 199 apartamentos. Sin contacto directo público — verificar con Administra PTY o en portería.
A17: =IF(B17="","",ROW()-1) | B17: PH Guayacán (Santa María) | C17: PH/Residencial | D17: Costa del Este | E17: Santa María, Costa del Este, Panamá | J17: No | K17: Sin verificar | L17: =IF(B17="","",IF(COUNTIFS($B$2:B17,B17,$D$2:D17,D17)>1,"SI","NO")) | M17: =IF(G17="","",IF(AND(ISNUMBER(SEARCH("@",G17)),ISNUMBER(SEARCH(".",G17,SEARCH("@",G17))),LEN(G17)-LEN(SUBSTITUTE(G17,"@",""))=1,MID(G17,SEARCH("@",G17)+1,1)<>".",RIGHT(G17,1)<>"."),"Válido","Revisar")) | N17: =IF(F17="","",IF(LEN(SUBSTITUTE(SUBSTITUTE(SUBSTITUTE(SUBSTITUTE(F17,"+507",""),"-",""),"(",""),")",""))=8,"Válido","Revisar")) | O17: Proyecto residencial de lujo. Sin contacto directo público — verificar con administradora o en portería.
A18: =IF(B18="","",ROW()-1) | B18: PH La Vista (Santa María Golf & Country Club) | C18: PH/Residencial | D18: Costa del Este | E18: Santa María Golf & Country Club, Panamá | J18: No | K18: Sin verificar | L18: =IF(B18="","",IF(COUNTIFS($B$2:B18,B18,$D$2:D18,D18)>1,"SI","NO")) | M18: =IF(G18="","",IF(AND(ISNUMBER(SEARCH("@",G18)),ISNUMBER(SEARCH(".",G18,SEARCH("@",G18))),LEN(G18)-LEN(SUBSTITUTE(G18,"@",""))=1,MID(G18,SEARCH("@",G18)+1,1)<>".",RIGHT(G18,1)<>"."),"Válido","Revisar")) | N18: =IF(F18="","",IF(LEN(SUBSTITUTE(SUBSTITUTE(SUBSTITUTE(SUBSTITUTE(F18,"+507",""),"-",""),"(",""),")",""))=8,"Válido","Revisar")) | O18: Torre residencial de 30 niveles. Sin contacto directo público — verificar con administradora o en portería.
A19: =IF(B19="","",ROW()-1) | B19: PH Marea (Costa del Este) | C19: PH/Residencial | D19: Costa del Este | E19: Costa del Este, Panamá | J19: No | K19: Sin verificar | L19: =IF(B19="","",IF(COUNTIFS($B$2:B19,B19,$D$2:D19,D19)>1,"SI","NO")) | M19: =IF(G19="","",IF(AND(ISNUMBER(SEARCH("@",G19)),ISNUMBER(SEARCH(".",G19,SEARCH("@",G19))),LEN(G19)-LEN(SUBSTITUTE(G19,"@",""))=1,MID(G19,SEARCH("@",G19)+1,1)<>".",RIGHT(G19,1)<>"."),"Válido","Revisar")) | N19: =IF(F19="","",IF(LEN(SUBSTITUTE(SUBSTITUTE(SUBSTITUTE(SUBSTITUTE(F19,"+507",""),"-",""),"(",""),")",""))=8,"Válido","Revisar")) | O19: Sin contacto directo público — verificar con administradora o en portería.
A20: =IF(B20="","",ROW()-1) | B20: PH Ocean House (Santa María) | C20: PH/Residencial | D20: Costa del Este | E20: Santa María, Costa del Este, Panamá | J20: No | K20: Sin verificar | L20: =IF(B20="","",IF(COUNTIFS($B$2:B20,B20,$D$2:D20,D20)>1,"SI","NO")) | M20: =IF(G20="","",IF(AND(ISNUMBER(SEARCH("@",G20)),ISNUMBER(SEARCH(".",G20,SEARCH("@",G20))),LEN(G20)-LEN(SUBSTITUTE(G20,"@",""))=1,MID(G20,SEARCH("@",G20)+1,1)<>".",RIGHT(G20,1)<>"."),"Válido","Revisar")) | N20: =IF(F20="","",IF(LEN(SUBSTITUTE(SUBSTITUTE(SUBSTITUTE(SUBSTITUTE(F20,"+507",""),"-",""),"(",""),")",""))=8,"Válido","Revisar")) | O20: Sin contacto directo público — verificar con administradora o en portería.
A21: =IF(B21="","",ROW()-1) | B21: Reserva de Versalles (Oficina Provivienda) | C21: PH/Residencial | D21: Reserva de Versalles | E21: Ave. Balboa, Torre Davivienda, PB y niveles 22-23, Panamá | F21: 300-0806 / 304-9844 | J21: No | K21: Sin verificar | L21: =IF(B21="","",IF(COUNTIFS($B$2:B21,B21,$D$2:D21,D21)>1,"SI","NO")) | M21: =IF(G21="","",IF(AND(ISNUMBER(SEARCH("@",G21)),ISNUMBER(SEARCH(".",G21,SEARCH("@",G21))),LEN(G21)-LEN(SUBSTITUTE(G21,"@",""))=1,MID(G21,SEARCH("@",G21)+1,1)<>".",RIGHT(G21,1)<>"."),"Válido","Revisar")) | N21: =IF(F21="","",IF(LEN(SUBSTITUTE(SUBSTITUTE(SUBSTITUTE(SUBSTITUTE(F21,"+507",""),"-",""),"(",""),")",""))=8,"Válido","Revisar")) | O21: Oficina de ventas/administración de Grupo Provivienda. Confirmar si ya hay administración de PH independiente para el edificio construido.
A22: =IF(B22="","",ROW()-1) | B22: H & H Facility Management (administradora de PH) | C22: Otro | D22: Otra zona Ciudad de Panamá | E22: Condado Plaza, Local No. 4, Panamá | H22: hhfacilitymanagement.com | J22: No | K22: Sin verificar | L22: =IF(B22="","",IF(COUNTIFS($B$2:B22,B22,$D$2:D22,D22)>1,"SI","NO")) | M22: =IF(G22="","",IF(AND(ISNUMBER(SEARCH("@",G22)),ISNUMBER(SEARCH(".",G22,SEARCH("@",G22))),LEN(G22)-LEN(SUBSTITUTE(G22,"@",""))=1,MID(G22,SEARCH("@",G22)+1,1)<>".",RIGHT(G22,1)<>"."),"Válido","Revisar")) | N22: =IF(F22="","",IF(LEN(SUBSTITUTE(SUBSTITUTE(SUBSTITUTE(SUBSTITUTE(F22,"+507",""),"-",""),"(",""),")",""))=8,"Válido","Revisar")) | O22: Administradora multi-PH, 8 años de experiencia. Teléfono/correo no público — usar formulario del sitio web.
A23: =IF(B23="","",ROW()-1) | B23: Panama Horizon (administra PH Mystic Village y otros en Don Bosco) | C23: Otro | D23: Don Bosco | E23: Avenida Rodolfo Aguilera, PH Mystic Village, Don Bosco, Panamá | F23: +507 273-2581 / 6307-8957 | G23: contacto@panamahorizon.net | H23: panamahorizon.net | J23: No | K23: Sin verificar | L23: =IF(B23="","",IF(COUNTIFS($B$2:B23,B23,$D$2:D23,D23)>1,"SI","NO")) | M23: =IF(G23="","",IF(AND(ISNUMBER(SEARCH("@",G23)),ISNUMBER(SEARCH(".",G23,SEARCH("@",G23))),LEN(G23)-LEN(SUBSTITUTE(G23,"@",""))=1,MID(G23,SEARCH("@",G23)+1,1)<>".",RIGHT(G23,1)<>"."),"Válido","Revisar")) | N23: =IF(F23="","",IF(LEN(SUBSTITUTE(SUBSTITUTE(SUBSTITUTE(SUBSTITUTE(F23,"+507",""),"-",""),"(",""),")",""))=8,"Válido","Revisar")) | O23: Administradora de PH con oficina en Don Bosco (también opera en Boquete). Buen punto de entrada para varios residenciales del sector.
A24: =IF(B24="","",ROW()-1) | B24: Edificio P.H. Brasil 405 (oficinas) | C24: Oficina | D24: Vía Brasil | E24: P.H. Brasil 405, Nivel 1200, Oficina 8-H, Vía Brasil, Panamá | J24: No | K24: Sin verificar | L24: =IF(B24="","",IF(COUNTIFS($B$2:B24,B24,$D$2:D24,D24)>1,"SI","NO")) | M24: =IF(G24="","",IF(AND(ISNUMBER(SEARCH("@",G24)),ISNUMBER(SEARCH(".",G24,SEARCH("@",G24))),LEN(G24)-LEN(SUBSTITUTE(G24,"@",""))=1,MID(G24,SEARCH("@",G24)+1,1)<>".",RIGHT(G24,1)<>"."),"Válido","Revisar")) | N24: =IF(F24="","",IF(LEN(SUBSTITUTE(SUBSTITUTE(SUBSTITUTE(SUBSTITUTE(F24,"+507",""),"-",""),"(",""),")",""))=8,"Válido","Revisar")) | O24: Edificio de oficinas identificado en Vía Brasil. No se encontró teléfono directo de administración — verificar en portería.
A25: =IF(B25="","",ROW()-1) | B25: Balboa Office Center (BOC) | C25: Oficina | D25: Avenida Balboa / Cinta Costera | E25: Ave. Balboa, Cinta Costera, Piso 12, Panamá | J25: No | K25: Sin verificar | L25: =IF(B25="","",IF(COUNTIFS($B$2:B25,B25,$D$2:D25,D25)>1,"SI","NO")) | M25: =IF(G25="","",IF(AND(ISNUMBER(SEARCH("@",G25)),ISNUMBER(SEARCH(".",G25,SEARCH("@",G25))),LEN(G25)-LEN(SUBSTITUTE(G25,"@",""))=1,MID(G25,SEARCH("@",G25)+1,1)<>".",RIGHT(G25,1)<>"."),"Válido","Revisar")) | N25: =IF(F25="","",IF(LEN(SUBSTITUTE(SUBSTITUTE(SUBSTITUTE(SUBSTITUTE(F25,"+507",""),"-",""),"(",""),")",""))=8,"Válido","Revisar")) | O25: Centro de oficinas moderno de varios pisos. No se encontró teléfono de administración en la búsqueda — confirmar vía sitio web o portería.
A26: =IF(B26="","",ROW()-1) | B26: Torre BAC (oficinas, Avenida Balboa) | C26: Oficina | D26: Avenida Balboa / Cinta Costera | E26: Avenida Balboa, con vista a la Cinta Costera, Panamá | J26: No | K26: Sin verificar | L26: =IF(B26="","",IF(COUNTIFS($B$2:B26,B26,$D$2:D26,D26)>1,"SI","NO")) | M26: =IF(G26="","",IF(AND(ISNUMBER(SEARCH("@",G26)),ISNUMBER(SEARCH(".",G26,SEARCH("@",G26))),LEN(G26)-LEN(SUBSTITUTE(G26,"@",""))=1,MID(G26,SEARCH("@",G26)+1,1)<>".",RIGHT(G26,1)<>"."),"Válido","Revisar")) | N26: =IF(F26="","",IF(LEN(SUBSTITUTE(SUBSTITUTE(SUBSTITUTE(SUBSTITUTE(F26,"+507",""),"-",""),"(",""),")",""))=8,"Válido","Revisar")) | O26: Torre de oficinas. Sin contacto directo público — verificar en portería o sitio del banco BAC.
A27: =IF(B27="","",ROW()-1) | B27: PH Torres de Versalles I | C27: PH/Residencial | D27: Versalles PH1 | E27: Zona Este, cerca aeropuerto de Tocumen, Panamá | F27: +507 6678-7895 | J27: No | K27: Sin verificar | L27: =IF(B27="","",IF(COUNTIFS($B$2:B27,B27,$D$2:D27,D27)>1,"SI","NO")) | M27: =IF(G27="","",IF(AND(ISNUMBER(SEARCH("@",G27)),ISNUMBER(SEARCH(".",G27,SEARCH("@",G27))),LEN(G27)-LEN(SUBSTITUTE(G27,"@",""))=1,MID(G27,SEARCH("@",G27)+1,1)<>".",RIGHT(G27,1)<>"."),"Válido","Revisar")) | N27: =IF(F27="","",IF(LEN(SUBSTITUTE(SUBSTITUTE(SUBSTITUTE(SUBSTITUTE(F27,"+507",""),"-",""),"(",""),")",""))=8,"Válido","Revisar")) | O27: Existencia confirmada: 8 torres, desarrollador Grupo Provivienda, reseñas mixtas en plataformas inmobiliarias. Verificar en persona si corresponde exactamente a 'Versalles PH1' que manejas.
A28: =IF(B28="","",ROW()-1) | B28: PH Torres de Versalles II | C28: PH/Residencial | D28: Versalles PH2 | E28: Ave. Costanera, Versalles, Juan Díaz, Panamá | F28: 304-9844 | H28: gprovivienda.com | J28: No | K28: Sin verificar | L28: =IF(B28="","",IF(COUNTIFS($B$2:B28,B28,$D$2:D28,D28)>1,"SI","NO")) | M28: =IF(G28="","",IF(AND(ISNUMBER(SEARCH("@",G28)),ISNUMBER(SEARCH(".",G28,SEARCH("@",G28))),LEN(G28)-LEN(SUBSTITUTE(G28,"@",""))=1,MID(G28,SEARCH("@",G28)+1,1)<>".",RIGHT(G28,1)<>"."),"Válido","Revisar")) | N28: =IF(F28="","",IF(LEN(SUBSTITUTE(SUBSTITUTE(SUBSTITUTE(SUBSTITUTE(F28,"+507",""),"-",""),"(",""),")",""))=8,"Válido","Revisar")) | O28: Proyecto de Grupo Provivienda (mismo desarrollador de Versalles I y Reserva de Versalles). Teléfono es línea general de ventas de Provivienda — confirmar contacto específico de administración del PH ya entregado.
A29: =IF(B29="","",ROW()-1) | B29: Grupo Provivienda (oficina central — desarrollador de todo el sector Versalles) | C29: Otro | D29: Otra zona Ciudad de Panamá | E29: Ave. Balboa, Torre Davivienda, Panamá | F29: 304-9844 / 304-9807 / 304-9877 / 304-9830 / 304-9836 / 304-9832 / 304-9835 / 304-9813 | H29: gprovivienda.com | J29: No | K29: Sin verificar | L29: =IF(B29="","",IF(COUNTIFS($B$2:B29,B29,$D$2:D29,D29)>1,"SI","NO")) | M29: =IF(G29="","",IF(AND(ISNUMBER(SEARCH("@",G29)),ISNUMBER(SEARCH(".",G29,SEARCH("@",G29))),LEN(G29)-LEN(SUBSTITUTE(G29,"@",""))=1,MID(G29,SEARCH("@",G29)+1,1)<>".",RIGHT(G29,1)<>"."),"Válido","Revisar")) | N29: =IF(F29="","",IF(LEN(SUBSTITUTE(SUBSTITUTE(SUBSTITUTE(SUBSTITUTE(F29,"+507",""),"-",""),"(",""),")",""))=8,"Válido","Revisar")) | O29: Desarrollador de Torres de Versalles I y II, Reserva de Versalles, Riviera del Golf (Coco del Mar), Van Gogh, Torres de Cantabria y otros. Contactarlos aquí puede abrir varios PH del mismo grupo de una vez — pedir el contacto de administración de cada proyecto ya entregado (ellos no administran una vez vendido, pero pueden referir a la junta de propietarios).
A30: =IF(B30="","",ROW()-1) | B30: Riviera del Golf (Coco del Mar) | C30: PH/Residencial | D30: Otra zona Ciudad de Panamá | E30: Coco del Mar, Panamá | F30: 304-9844 | H30: gprovivienda.com | J30: No | K30: Sin verificar | L30: =IF(B30="","",IF(COUNTIFS($B$2:B30,B30,$D$2:D30,D30)>1,"SI","NO")) | M30: =IF(G30="","",IF(AND(ISNUMBER(SEARCH("@",G30)),ISNUMBER(SEARCH(".",G30,SEARCH("@",G30))),LEN(G30)-LEN(SUBSTITUTE(G30,"@",""))=1,MID(G30,SEARCH("@",G30)+1,1)<>".",RIGHT(G30,1)<>"."),"Válido","Revisar")) | N30: =IF(F30="","",IF(LEN(SUBSTITUTE(SUBSTITUTE(SUBSTITUTE(SUBSTITUTE(F30,"+507",""),"-",""),"(",""),")",""))=8,"Válido","Revisar")) | O30: Proyecto de Grupo Provivienda con vista al mar en Coco del Mar, cerca de Costa del Este. Teléfono es línea general de ventas — confirmar administración del PH ya entregado.
A31: =IF(B31="","",ROW()-1) | B31: PH Sevilla | C31: PH/Residencial | D31: Costa del Este | E31: Torre 2000, Calle Greenbay, Costa del Este, Panamá | G31: administracion@phsevillapty.com | H31: phsevillapty.com | J31: No | K31: Sin verificar | L31: =IF(B31="","",IF(COUNTIFS($B$2:B31,B31,$D$2:D31,D31)>1,"SI","NO")) | M31: =IF(G31="","",IF(AND(ISNUMBER(SEARCH("@",G31)),ISNUMBER(SEARCH(".",G31,SEARCH("@",G31))),LEN(G31)-LEN(SUBSTITUTE(G31,"@",""))=1,MID(G31,SEARCH("@",G31)+1,1)<>".",RIGHT(G31,1)<>"."),"Válido","Revisar")) | N31: =IF(F31="","",IF(LEN(SUBSTITUTE(SUBSTITUTE(SUBSTITUTE(SUBSTITUTE(F31,"+507",""),"-",""),"(",""),")",""))=8,"Válido","Revisar")) | O31: Administración confirmada vía sitio web oficial. Reportes financieros disponibles en el sitio.
A32: =IF(B32="","",ROW()-1) | B32: P.H. Parques del Mar | C32: PH/Residencial | D32: Costa del Este | E32: Parque Lefevre, Panamá | J32: No | K32: Sin verificar | L32: =IF(B32="","",IF(COUNTIFS($B$2:B32,B32,$D$2:D32,D32)>1,"SI","NO")) | M32: =IF(G32="","",IF(AND(ISNUMBER(SEARCH("@",G32)),ISNUMBER(SEARCH(".",G32,SEARCH("@",G32))),LEN(G32)-LEN(SUBSTITUTE(G32,"@",""))=1,MID(G32,SEARCH("@",G32)+1,1)<>".",RIGHT(G32,1)<>"."),"Válido","Revisar")) | N32: =IF(F32="","",IF(LEN(SUBSTITUTE(SUBSTITUTE(SUBSTITUTE(SUBSTITUTE(F32,"+507",""),"-",""),"(",""),")",""))=8,"Válido","Revisar")) | O32: Encontrado vía TomTom Maps (POI residencial confirmado, existencia real). Sin teléfono público listado — verificar en portería o con la administración en persona.
A33: =IF(B33="","",ROW()-1) | B33: P.H. Castellammare | C33: PH/Residencial | D33: Costa del Este | E33: Parque Lefevre, Panamá | J33: No | K33: Sin verificar | L33: =IF(B33="","",IF(COUNTIFS($B$2:B33,B33,$D$2:D33,D33)>1,"SI","NO")) | M33: =IF(G33="","",IF(AND(ISNUMBER(SEARCH("@",G33)),ISNUMBER(SEARCH(".",G33,SEARCH("@",G33))),LEN(G33)-LEN(SUBSTITUTE(G33,"@",""))=1,MID(G33,SEARCH("@",G33)+1,1)<>".",RIGHT(G33,1)<>"."),"Válido","Revisar")) | N33: =IF(F33="","",IF(LEN(SUBSTITUTE(SUBSTITUTE(SUBSTITUTE(SUBSTITUTE(F33,"+507",""),"-",""),"(",""),")",""))=8,"Válido","Revisar")) | O33: Encontrado vía TomTom Maps (POI residencial confirmado, existencia real). Sin teléfono público listado — verificar en portería o con la administración en persona.
A34: =IF(B34="","",ROW()-1) | B34: P.H. Mirador | C34: PH/Residencial | D34: Costa del Este | E34: Parque Lefevre, Panamá | J34: No | K34: Sin verificar | L34: =IF(B34="","",IF(COUNTIFS($B$2:B34,B34,$D$2:D34,D34)>1,"SI","NO")) | M34: =IF(G34="","",IF(AND(ISNUMBER(SEARCH("@",G34)),ISNUMBER(SEARCH(".",G34,SEARCH("@",G34))),LEN(G34)-LEN(SUBSTITUTE(G34,"@",""))=1,MID(G34,SEARCH("@",G34)+1,1)<>".",RIGHT(G34,1)<>"."),"Válido","Revisar")) | N34: =IF(F34="","",IF(LEN(SUBSTITUTE(SUBSTITUTE(SUBSTITUTE(SUBSTITUTE(F34,"+507",""),"-",""),"(",""),")",""))=8,"Válido","Revisar")) | O34: Encontrado vía TomTom Maps (POI residencial confirmado, existencia real). Sin teléfono público listado — verificar en portería o con la administración en persona.
A35: =IF(B35="","",ROW()-1) | B35: Costa del Mar | C35: PH/Residencial | D35: Costa del Este | E35: Parque Lefevre, Panamá | J35: No | K35: Sin verificar | L35: =IF(B35="","",IF(COUNTIFS($B$2:B35,B35,$D$2:D35,D35)>1,"SI","NO")) | M35: =IF(G35="","",IF(AND(ISNUMBER(SEARCH("@",G35)),ISNUMBER(SEARCH(".",G35,SEARCH("@",G35))),LEN(G35)-LEN(SUBSTITUTE(G35,"@",""))=1,MID(G35,SEARCH("@",G35)+1,1)<>".",RIGHT(G35,1)<>"."),"Válido","Revisar")) | N35: =IF(F35="","",IF(LEN(SUBSTITUTE(SUBSTITUTE(SUBSTITUTE(SUBSTITUTE(F35,"+507",""),"-",""),"(",""),")",""))=8,"Válido","Revisar")) | O35: Encontrado vía TomTom Maps (POI residencial confirmado, existencia real). Sin teléfono público listado — verificar en portería o con la administración en persona.
A36: =IF(B36="","",ROW()-1) | B36: P.H. Lumiere | C36: PH/Residencial | D36: Costa del Este | E36: Parque Lefevre, Panamá | J36: No | K36: Sin verificar | L36: =IF(B36="","",IF(COUNTIFS($B$2:B36,B36,$D$2:D36,D36)>1,"SI","NO")) | M36: =IF(G36="","",IF(AND(ISNUMBER(SEARCH("@",G36)),ISNUMBER(SEARCH(".",G36,SEARCH("@",G36))),LEN(G36)-LEN(SUBSTITUTE(G36,"@",""))=1,MID(G36,SEARCH("@",G36)+1,1)<>".",RIGHT(G36,1)<>"."),"Válido","Revisar")) | N36: =IF(F36="","",IF(LEN(SUBSTITUTE(SUBSTITUTE(SUBSTITUTE(SUBSTITUTE(F36,"+507",""),"-",""),"(",""),")",""))=8,"Válido","Revisar")) | O36: Encontrado vía TomTom Maps (POI residencial confirmado, existencia real). Sin teléfono público listado — verificar en portería o con la administración en persona.
A37: =IF(B37="","",ROW()-1) | B37: P.H. Riverside | C37: PH/Residencial | D37: Costa del Este | E37: Parque Lefevre, Panamá | J37: No | K37: Sin verificar | L37: =IF(B37="","",IF(COUNTIFS($B$2:B37,B37,$D$2:D37,D37)>1,"SI","NO")) | M37: =IF(G37="","",IF(AND(ISNUMBER(SEARCH("@",G37)),ISNUMBER(SEARCH(".",G37,SEARCH("@",G37))),LEN(G37)-LEN(SUBSTITUTE(G37,"@",""))=1,MID(G37,SEARCH("@",G37)+1,1)<>".",RIGHT(G37,1)<>"."),"Válido","Revisar")) | N37: =IF(F37="","",IF(LEN(SUBSTITUTE(SUBSTITUTE(SUBSTITUTE(SUBSTITUTE(F37,"+507",""),"-",""),"(",""),")",""))=8,"Válido","Revisar")) | O37: Encontrado vía TomTom Maps (POI residencial confirmado, existencia real). Sin teléfono público listado — verificar en portería o con la administración en persona.
A38: =IF(B38="","",ROW()-1) | B38: P.H. Mikonos | C38: PH/Residencial | D38: Costa del Este | E38: Parque Lefevre, Panamá | J38: No | K38: Sin verificar | L38: =IF(B38="","",IF(COUNTIFS($B$2:B38,B38,$D$2:D38,D38)>1,"SI","NO")) | M38: =IF(G38="","",IF(AND(ISNUMBER(SEARCH("@",G38)),ISNUMBER(SEARCH(".",G38,SEARCH("@",G38))),LEN(G38)-LEN(SUBSTITUTE(G38,"@",""))=1,MID(G38,SEARCH("@",G38)+1,1)<>".",RIGHT(G38,1)<>"."),"Válido","Revisar")) | N38: =IF(F38="","",IF(LEN(SUBSTITUTE(SUBSTITUTE(SUBSTITUTE(SUBSTITUTE(F38,"+507",""),"-",""),"(",""),")",""))=8,"Válido","Revisar")) | O38: Encontrado vía TomTom Maps (POI residencial confirmado, existencia real). Sin teléfono público listado — verificar en portería o con la administración en persona.
A39: =IF(B39="","",ROW()-1) | B39: Villas de Costa del Este | C39: PH/Residencial | D39: Costa del Este | E39: Parque Lefevre, Panamá | J39: No | K39: Sin verificar | L39: =IF(B39="","",IF(COUNTIFS($B$2:B39,B39,$D$2:D39,D39)>1,"SI","NO")) | M39: =IF(G39="","",IF(AND(ISNUMBER(SEARCH("@",G39)),ISNUMBER(SEARCH(".",G39,SEARCH("@",G39))),LEN(G39)-LEN(SUBSTITUTE(G39,"@",""))=1,MID(G39,SEARCH("@",G39)+1,1)<>".",RIGHT(G39,1)<>"."),"Válido","Revisar")) | N39: =IF(F39="","",IF(LEN(SUBSTITUTE(SUBSTITUTE(SUBSTITUTE(SUBSTITUTE(F39,"+507",""),"-",""),"(",""),")",""))=8,"Válido","Revisar")) | O39: Encontrado vía TomTom Maps (POI residencial confirmado, existencia real). Sin teléfono público listado — verificar en portería o con la administración en persona.
A40: =IF(B40="","",ROW()-1) | B40: Reparto Nuevo Panamá | C40: PH/Residencial | D40: Costa del Este | E40: Calle 4, Parque Lefevre, Panamá | J40: No | K40: Sin verificar | L40: =IF(B40="","",IF(COUNTIFS($B$2:B40,B40,$D$2:D40,D40)>1,"SI","NO")) | M40: =IF(G40="","",IF(AND(ISNUMBER(SEARCH("@",G40)),ISNUMBER(SEARCH(".",G40,SEARCH("@",G40))),LEN(G40)-LEN(SUBSTITUTE(G40,"@",""))=1,MID(G40,SEARCH("@",G40)+1,1)<>".",RIGHT(G40,1)<>"."),"Válido","Revisar")) | N40: =IF(F40="","",IF(LEN(SUBSTITUTE(SUBSTITUTE(SUBSTITUTE(SUBSTITUTE(F40,"+507",""),"-",""),"(",""),")",""))=8,"Válido","Revisar")) | O40: Encontrado vía TomTom Maps (POI residencial confirmado, existencia real). Sin teléfono público listado — verificar en portería o con la administración en persona.
A41: =IF(B41="","",ROW()-1) | B41: Villa del Rey | C41: PH/Residencial | D41: Costa del Este | E41: Calle Villa del Rey, Parque Lefevre, Panamá | J41: No | K41: Sin verificar | L41: =IF(B41="","",IF(COUNTIFS($B$2:B41,B41,$D$2:D41,D41)>1,"SI","NO")) | M41: =IF(G41="","",IF(AND(ISNUMBER(SEARCH("@",G41)),ISNUMBER(SEARCH(".",G41,SEARCH("@",G41))),LEN(G41)-LEN(SUBSTITUTE(G41,"@",""))=1,MID(G41,SEARCH("@",G41)+1,1)<>".",RIGHT(G41,1)<>"."),"Válido","Revisar")) | N41: =IF(F41="","",IF(LEN(SUBSTITUTE(SUBSTITUTE(SUBSTITUTE(SUBSTITUTE(F41,"+507",""),"-",""),"(",""),")",""))=8,"Válido","Revisar")) | O41: Encontrado vía TomTom Maps (POI residencial confirmado, existencia real). Sin teléfono público listado — verificar en portería o con la administración en persona.
A42: =IF(B42="","",ROW()-1) | B42: La Fontana | C42: PH/Residencial | D42: Costa del Este | E42: Calle Benjamin Quintero, Parque Lefevre, Panamá | F42: (2) 265-1272 | J42: No | K42: Sin verificar | L42: =IF(B42="","",IF(COUNTIFS($B$2:B42,B42,$D$2:D42,D42)>1,"SI","NO")) | M42: =IF(G42="","",IF(AND(ISNUMBER(SEARCH("@",G42)),ISNUMBER(SEARCH(".",G42,SEARCH("@",G42))),LEN(G42)-LEN(SUBSTITUTE(G42,"@",""))=1,MID(G42,SEARCH("@",G42)+1,1)<>".",RIGHT(G42,1)<>"."),"Válido","Revisar")) | N42: =IF(F42="","",IF(LEN(SUBSTITUTE(SUBSTITUTE(SUBSTITUTE(SUBSTITUTE(F42,"+507",""),"-",""),"(",""),")",""))=8,"Válido","Revisar")) | O42: Teléfono encontrado en directorio, pero la dirección de esa ficha aparece en Obarrio, no en Parque Lefevre — podría ser otro 'La Fontana'. Confirmar antes de llamar.
A43: =IF(B43="","",ROW()-1) | B43: Puente del Rey | C43: PH/Residencial | D43: Costa del Este | E43: Parque Lefevre, Panamá | J43: No | K43: Sin verificar | L43: =IF(B43="","",IF(COUNTIFS($B$2:B43,B43,$D$2:D43,D43)>1,"SI","NO")) | M43: =IF(G43="","",IF(AND(ISNUMBER(SEARCH("@",G43)),ISNUMBER(SEARCH(".",G43,SEARCH("@",G43))),LEN(G43)-LEN(SUBSTITUTE(G43,"@",""))=1,MID(G43,SEARCH("@",G43)+1,1)<>".",RIGHT(G43,1)<>"."),"Válido","Revisar")) | N43: =IF(F43="","",IF(LEN(SUBSTITUTE(SUBSTITUTE(SUBSTITUTE(SUBSTITUTE(F43,"+507",""),"-",""),"(",""),")",""))=8,"Válido","Revisar")) | O43: Encontrado vía TomTom Maps (POI residencial confirmado, existencia real). Sin teléfono público listado — verificar en portería o con la administración en persona.
A44: =IF(B44="","",ROW()-1) | B44: Jardines de Costa del Este | C44: PH/Residencial | D44: Costa del Este | E44: Parque Lefevre, Panamá | J44: No | K44: Sin verificar | L44: =IF(B44="","",IF(COUNTIFS($B$2:B44,B44,$D$2:D44,D44)>1,"SI","NO")) | M44: =IF(G44="","",IF(AND(ISNUMBER(SEARCH("@",G44)),ISNUMBER(SEARCH(".",G44,SEARCH("@",G44))),LEN(G44)-LEN(SUBSTITUTE(G44,"@",""))=1,MID(G44,SEARCH("@",G44)+1,1)<>".",RIGHT(G44,1)<>"."),"Válido","Revisar")) | N44: =IF(F44="","",IF(LEN(SUBSTITUTE(SUBSTITUTE(SUBSTITUTE(SUBSTITUTE(F44,"+507",""),"-",""),"(",""),")",""))=8,"Válido","Revisar")) | O44: Encontrado vía TomTom Maps (POI residencial confirmado, existencia real). Sin teléfono público listado — verificar en portería o con la administración en persona.
A45: =IF(B45="","",ROW()-1) | B45: Costa Azul (Juan Díaz) | C45: PH/Residencial | D45: Costa del Este | E45: Calle Arrecife, Juan Díaz, Panamá | J45: No | K45: Sin verificar | L45: =IF(B45="","",IF(COUNTIFS($B$2:B45,B45,$D$2:D45,D45)>1,"SI","NO")) | M45: =IF(G45="","",IF(AND(ISNUMBER(SEARCH("@",G45)),ISNUMBER(SEARCH(".",G45,SEARCH("@",G45))),LEN(G45)-LEN(SUBSTITUTE(G45,"@",""))=1,MID(G45,SEARCH("@",G45)+1,1)<>".",RIGHT(G45,1)<>"."),"Válido","Revisar")) | N45: =IF(F45="","",IF(LEN(SUBSTITUTE(SUBSTITUTE(SUBSTITUTE(SUBSTITUTE(F45,"+507",""),"-",""),"(",""),")",""))=8,"Válido","Revisar")) | O45: Encontrado vía TomTom Maps (POI residencial confirmado, existencia real). Sin teléfono público listado — verificar en portería o con la administración en persona.
A46: =IF(B46="","",ROW()-1) | B46: Casa Blanca | C46: PH/Residencial | D46: Costa del Este | E46: Parque Lefevre, Panamá | J46: No | K46: Sin verificar | L46: =IF(B46="","",IF(COUNTIFS($B$2:B46,B46,$D$2:D46,D46)>1,"SI","NO")) | M46: =IF(G46="","",IF(AND(ISNUMBER(SEARCH("@",G46)),ISNUMBER(SEARCH(".",G46,SEARCH("@",G46))),LEN(G46)-LEN(SUBSTITUTE(G46,"@",""))=1,MID(G46,SEARCH("@",G46)+1,1)<>".",RIGHT(G46,1)<>"."),"Válido","Revisar")) | N46: =IF(F46="","",IF(LEN(SUBSTITUTE(SUBSTITUTE(SUBSTITUTE(SUBSTITUTE(F46,"+507",""),"-",""),"(",""),")",""))=8,"Válido","Revisar")) | O46: Encontrado vía TomTom Maps (POI residencial confirmado, existencia real). Sin teléfono público listado — verificar en portería o con la administración en persona.
A47: =IF(B47="","",ROW()-1) | B47: Costa Bay | C47: PH/Residencial | D47: Costa del Este | E47: Calle Chipre, Juan Díaz, Panamá | J47: No | K47: Sin verificar | L47: =IF(B47="","",IF(COUNTIFS($B$2:B47,B47,$D$2:D47,D47)>1,"SI","NO")) | M47: =IF(G47="","",IF(AND(ISNUMBER(SEARCH("@",G47)),ISNUMBER(SEARCH(".",G47,SEARCH("@",G47))),LEN(G47)-LEN(SUBSTITUTE(G47,"@",""))=1,MID(G47,SEARCH("@",G47)+1,1)<>".",RIGHT(G47,1)<>"."),"Válido","Revisar")) | N47: =IF(F47="","",IF(LEN(SUBSTITUTE(SUBSTITUTE(SUBSTITUTE(SUBSTITUTE(F47,"+507",""),"-",""),"(",""),")",""))=8,"Válido","Revisar")) | O47: Encontrado vía TomTom Maps (POI residencial confirmado, existencia real). Sin teléfono público listado — verificar en portería o con la administración en persona.
A48: =IF(B48="","",ROW()-1) | B48: P.H. Residencial Santa Elena | C48: PH/Residencial | D48: Costa del Este | E48: Parque Lefevre, Panamá | J48: No | K48: Sin verificar | L48: =IF(B48="","",IF(COUNTIFS($B$2:B48,B48,$D$2:D48,D48)>1,"SI","NO")) | M48: =IF(G48="","",IF(AND(ISNUMBER(SEARCH("@",G48)),ISNUMBER(SEARCH(".",G48,SEARCH("@",G48))),LEN(G48)-LEN(SUBSTITUTE(G48,"@",""))=1,MID(G48,SEARCH("@",G48)+1,1)<>".",RIGHT(G48,1)<>"."),"Válido","Revisar")) | N48: =IF(F48="","",IF(LEN(SUBSTITUTE(SUBSTITUTE(SUBSTITUTE(SUBSTITUTE(F48,"+507",""),"-",""),"(",""),")",""))=8,"Válido","Revisar")) | O48: Encontrado vía TomTom Maps (POI residencial confirmado, existencia real). Sin teléfono público listado — verificar en portería o con la administración en persona.
A49: =IF(B49="","",ROW()-1) | B49: Panamá Viejo (Cincuentenario) | C49: PH/Residencial | D49: Costa del Este | E49: Avenida Cincuentenario, Parque Lefevre, Panamá | J49: No | K49: Sin verificar | L49: =IF(B49="","",IF(COUNTIFS($B$2:B49,B49,$D$2:D49,D49)>1,"SI","NO")) | M49: =IF(G49="","",IF(AND(ISNUMBER(SEARCH("@",G49)),ISNUMBER(SEARCH(".",G49,SEARCH("@",G49))),LEN(G49)-LEN(SUBSTITUTE(G49,"@",""))=1,MID(G49,SEARCH("@",G49)+1,1)<>".",RIGHT(G49,1)<>"."),"Válido","Revisar")) | N49: =IF(F49="","",IF(LEN(SUBSTITUTE(SUBSTITUTE(SUBSTITUTE(SUBSTITUTE(F49,"+507",""),"-",""),"(",""),")",""))=8,"Válido","Revisar")) | O49: Encontrado vía TomTom Maps (POI residencial confirmado, existencia real). Sin teléfono público listado — verificar en portería o con la administración en persona.
A50: =IF(B50="","",ROW()-1) | B50: P.H. Acqua I | C50: PH/Residencial | D50: Costa del Este | E50: Juan Díaz, Panamá | J50: No | K50: Sin verificar | L50: =IF(B50="","",IF(COUNTIFS($B$2:B50,B50,$D$2:D50,D50)>1,"SI","NO")) | M50: =IF(G50="","",IF(AND(ISNUMBER(SEARCH("@",G50)),ISNUMBER(SEARCH(".",G50,SEARCH("@",G50))),LEN(G50)-LEN(SUBSTITUTE(G50,"@",""))=1,MID(G50,SEARCH("@",G50)+1,1)<>".",RIGHT(G50,1)<>"."),"Válido","Revisar")) | N50: =IF(F50="","",IF(LEN(SUBSTITUTE(SUBSTITUTE(SUBSTITUTE(SUBSTITUTE(F50,"+507",""),"-",""),"(",""),")",""))=8,"Válido","Revisar")) | O50: Encontrado vía TomTom Maps (POI residencial confirmado, existencia real). Sin teléfono público listado — verificar en portería o con la administración en persona.
A51: =IF(B51="","",ROW()-1) | B51: Costa Serena | C51: PH/Residencial | D51: Costa del Este | E51: Juan Díaz, Panamá | J51: No | K51: Sin verificar | L51: =IF(B51="","",IF(COUNTIFS($B$2:B51,B51,$D$2:D51,D51)>1,"SI","NO")) | M51: =IF(G51="","",IF(AND(ISNUMBER(SEARCH("@",G51)),ISNUMBER(SEARCH(".",G51,SEARCH("@",G51))),LEN(G51)-LEN(SUBSTITUTE(G51,"@",""))=1,MID(G51,SEARCH("@",G51)+1,1)<>".",RIGHT(G51,1)<>"."),"Válido","Revisar")) | N51: =IF(F51="","",IF(LEN(SUBSTITUTE(SUBSTITUTE(SUBSTITUTE(SUBSTITUTE(F51,"+507",""),"-",""),"(",""),")",""))=8,"Válido","Revisar")) | O51: Encontrado vía TomTom Maps (POI residencial confirmado, existencia real). Sin teléfono público listado — verificar en portería o con la administración en persona.
A52: =IF(B52="","",ROW()-1) | B52: P.H. Acqua II | C52: PH/Residencial | D52: Costa del Este | E52: Juan Díaz, Panamá | J52: No | K52: Sin verificar | L52: =IF(B52="","",IF(COUNTIFS($B$2:B52,B52,$D$2:D52,D52)>1,"SI","NO")) | M52: =IF(G52="","",IF(AND(ISNUMBER(SEARCH("@",G52)),ISNUMBER(SEARCH(".",G52,SEARCH("@",G52))),LEN(G52)-LEN(SUBSTITUTE(G52,"@",""))=1,MID(G52,SEARCH("@",G52)+1,1)<>".",RIGHT(G52,1)<>"."),"Válido","Revisar")) | N52: =IF(F52="","",IF(LEN(SUBSTITUTE(SUBSTITUTE(SUBSTITUTE(SUBSTITUTE(F52,"+507",""),"-",""),"(",""),")",""))=8,"Válido","Revisar")) | O52: Encontrado vía TomTom Maps (POI residencial confirmado, existencia real). Sin teléfono público listado — verificar en portería o con la administración en persona.
A53: =IF(B53="","",ROW()-1) | B53: Altos del Romeral | C53: PH/Residencial | D53: Costa del Este | E53: Calle La Gran Via, Parque Lefevre, Panamá | J53: No | K53: Sin verificar | L53: =IF(B53="","",IF(COUNTIFS($B$2:B53,B53,$D$2:D53,D53)>1,"SI","NO")) | M53: =IF(G53="","",IF(AND(ISNUMBER(SEARCH("@",G53)),ISNUMBER(SEARCH(".",G53,SEARCH("@",G53))),LEN(G53)-LEN(SUBSTITUTE(G53,"@",""))=1,MID(G53,SEARCH("@",G53)+1,1)<>".",RIGHT(G53,1)<>"."),"Válido","Revisar")) | N53: =IF(F53="","",IF(LEN(SUBSTITUTE(SUBSTITUTE(SUBSTITUTE(SUBSTITUTE(F53,"+507",""),"-",""),"(",""),")",""))=8,"Válido","Revisar")) | O53: Encontrado vía TomTom Maps (POI residencial confirmado, existencia real). Sin teléfono público listado — verificar en portería o con la administración en persona.
A54: =IF(B54="","",ROW()-1) | B54: Costa de Las Perlas | C54: PH/Residencial | D54: Costa del Este | E54: Calle Principal, Juan Díaz, Panamá | J54: No | K54: Sin verificar | L54: =IF(B54="","",IF(COUNTIFS($B$2:B54,B54,$D$2:D54,D54)>1,"SI","NO")) | M54: =IF(G54="","",IF(AND(ISNUMBER(SEARCH("@",G54)),ISNUMBER(SEARCH(".",G54,SEARCH("@",G54))),LEN(G54)-LEN(SUBSTITUTE(G54,"@",""))=1,MID(G54,SEARCH("@",G54)+1,1)<>".",RIGHT(G54,1)<>"."),"Válido","Revisar")) | N54: =IF(F54="","",IF(LEN(SUBSTITUTE(SUBSTITUTE(SUBSTITUTE(SUBSTITUTE(F54,"+507",""),"-",""),"(",""),")",""))=8,"Válido","Revisar")) | O54: Encontrado vía TomTom Maps (POI residencial confirmado, existencia real). Sin teléfono público listado — verificar en portería o con la administración en persona.
... A117: =IF(B117="","",ROW()-1) | B117: P.H. Ladera de la Cresta | C117: PH/Residencial | D117: El Cangrejo | E117: Calle La Colina, El Cangrejo, Panamá | J117: No | K117: Por verificar | L117: =IF(B117="","",IF(COUNTIFS($B$2:B117,B117,$D$2:D117,D117)>1,"SI","NO")) | M117: =IF(G117="","",IF(AND(ISNUMBER(SEARCH("@",G117)),ISNUMBER(SEARCH(".",G117,SEARCH("@",G117))),LEN(G117)-LEN(SUBSTITUTE(G117,"@",""))=1,MID(G117,SEARCH("@",G117)+1,1)<>".",RIGHT(G117,1)<>"."),"Válido","Revisar")) | N117: =IF(F117="","",IF(LEN(SUBSTITUTE(SUBSTITUTE(SUBSTITUTE(SUBSTITUTE(F117,"+507",""),"-",""),"(",""),")",""))=8,"Válido","Revisar")) | O117: Encontrado vía TomTom Maps (POI residencial confirmado, existencia real). Sin teléfono público listado — verificar en portería o con la administración en persona.
A118: =IF(B118="","",ROW()-1) | B118: P.H. Villas del Carmen | C118: PH/Residencial | D118: El Cangrejo | E118: Calle José de Fábrega (entre Universidad de Panamá y CSS), El Cangrejo, Panamá | G118: infovillaelcarmen@gmail.com | J118: No | K118: Por verificar | L118: =IF(B118="","",IF(COUNTIFS($B$2:B118,B118,$D$2:D118,D118)>1,"SI","NO")) | M118: =IF(G118="","",IF(AND(ISNUMBER(SEARCH("@",G118)),ISNUMBER(SEARCH(".",G118,SEARCH("@",G118))),LEN(G118)-LEN(SUBSTITUTE(G118,"@",""))=1,MID(G118,SEARCH("@",G118)+1,1)<>".",RIGHT(G118,1)<>"."),"Válido","Revisar")) | N118: =IF(F118="","",IF(LEN(SUBSTITUTE(SUBSTITUTE(SUBSTITUTE(SUBSTITUTE(F118,"+507",""),"-",""),"(",""),")",""))=8,"Válido","Revisar")) | O118: Correo encontrado pertenece a 'PH Villa el Carmen' (nombre muy similar, misma zona) — podría ser el mismo edificio con nombre ligeramente distinto o uno diferente. Confirmar antes de escribir.
A119: =IF(B119="","",ROW()-1) | B119: P.H. Villa Medici | C119: PH/Residencial | D119: Vía España | E119: Calle Otilia A. de Tejeira, Vía España, Panamá | J119: No | K119: Por verificar | L119: =IF(B119="","",IF(COUNTIFS($B$2:B119,B119,$D$2:D119,D119)>1,"SI","NO")) | M119: =IF(G119="","",IF(AND(ISNUMBER(SEARCH("@",G119)),ISNUMBER(SEARCH(".",G119,SEARCH("@",G119))),LEN(G119)-LEN(SUBSTITUTE(G119,"@",""))=1,MID(G119,SEARCH("@",G119)+1,1)<>".",RIGHT(G119,1)<>"."),"Válido","Revisar")) | N119: =IF(F119="","",IF(LEN(SUBSTITUTE(SUBSTITUTE(SUBSTITUTE(SUBSTITUTE(F119,"+507",""),"-",""),"(",""),")",""))=8,"Válido","Revisar")) | O119: Encontrado vía TomTom Maps (POI residencial confirmado, existencia real). Sin teléfono público listado — verificar en portería o con la administración en persona.
A120: =IF(B120="","",ROW()-1) | B120: Aires del Carmen | C120: PH/Residencial | D120: Vía España | E120: Vía España, Panamá | J120: No | K120: Por verificar | L120: =IF(B120="","",IF(COUNTIFS($B$2:B120,B120,$D$2:D120,D120)>1,"SI","NO")) | M120: =IF(G120="","",IF(AND(ISNUMBER(SEARCH("@",G120)),ISNUMBER(SEARCH(".",G120,SEARCH("@",G120))),LEN(G120)-LEN(SUBSTITUTE(G120,"@",""))=1,MID(G120,SEARCH("@",G120)+1,1)<>".",RIGHT(G120,1)<>"."),"Válido","Revisar")) | N120: =IF(F120="","",IF(LEN(SUBSTITUTE(SUBSTITUTE(SUBSTITUTE(SUBSTITUTE(F120,"+507",""),"-",""),"(",""),")",""))=8,"Válido","Revisar")) | O120: Encontrado vía TomTom Maps (POI residencial confirmado, existencia real). Sin teléfono público listado — verificar en portería o con la administración en persona.
A121: =IF(B121="","",ROW()-1) | B121: Balmoral Gardens | C121: PH/Residencial | D121: Pedregal | E121: Calle 1ra Oeste, Urb. Balmoral, Pedregal, Panamá | J121: No | K121: Sin verificar | L121: =IF(B121="","",IF(COUNTIFS($B$2:B121,B121,$D$2:D121,D121)>1,"SI","NO")) | M121: =IF(G121="","",IF(AND(ISNUMBER(SEARCH("@",G121)),ISNUMBER(SEARCH(".",G121,SEARCH("@",G121))),LEN(G121)-LEN(SUBSTITUTE(G121,"@",""))=1,MID(G121,SEARCH("@",G121)+1,1)<>".",RIGHT(G121,1)<>"."),"Válido","Revisar")) | N121: =IF(F121="","",IF(LEN(SUBSTITUTE(SUBSTITUTE(SUBSTITUTE(SUBSTITUTE(F121,"+507",""),"-",""),"(",""),")",""))=8,"Válido","Revisar")) | O121: Proyecto de BAU Panamá / Balmoral Gardens S.A. Sin teléfono de administración público — solo formulario de contacto de ventas en baupanama.com. Verificar en persona.
A122: =IF(B122="","",ROW()-1) | B122: PH Terrazas del Balmoral | C122: PH/Residencial | D122: Pedregal | E122: Vía C. Rana de Oro, Pedregal, Panamá | J122: No | K122: Sin verificar | L122: =IF(B122="","",IF(COUNTIFS($B$2:B122,B122,$D$2:D122,D122)>1,"SI","NO")) | M122: =IF(G122="","",IF(AND(ISNUMBER(SEARCH("@",G122)),ISNUMBER(SEARCH(".",G122,SEARCH("@",G122))),LEN(G122)-LEN(SUBSTITUTE(G122,"@",""))=1,MID(G122,SEARCH("@",G122)+1,1)<>".",RIGHT(G122,1)<>"."),"Válido","Revisar")) | N122: =IF(F122="","",IF(LEN(SUBSTITUTE(SUBSTITUTE(SUBSTITUTE(SUBSTITUTE(F122,"+507",""),"-",""),"(",""),")",""))=8,"Válido","Revisar")) | O122: Confirmado en listados inmobiliarios (Remax, Casa Solution). Sin teléfono de administración público — verificar en persona.
A123: =IF(B123="","",ROW()-1) | B123: PH Balmoral | C123: PH/Residencial | D123: Pedregal | E123: Urb. Balmoral, Pedregal, Panamá | J123: No | K123: Sin verificar | L123: =IF(B123="","",IF(COUNTIFS($B$2:B123,B123,$D$2:D123,D123)>1,"SI","NO")) | M123: =IF(G123="","",IF(AND(ISNUMBER(SEARCH("@",G123)),ISNUMBER(SEARCH(".",G123,SEARCH("@",G123))),LEN(G123)-LEN(SUBSTITUTE(G123,"@",""))=1,MID(G123,SEARCH("@",G123)+1,1)<>".",RIGHT(G123,1)<>"."),"Válido","Revisar")) | N123: =IF(F123="","",IF(LEN(SUBSTITUTE(SUBSTITUTE(SUBSTITUTE(SUBSTITUTE(F123,"+507",""),"-",""),"(",""),")",""))=8,"Válido","Revisar")) | O123: Nombre genérico de la urbanización Balmoral — podría referirse al mismo complejo que Balmoral Gardens o Terrazas del Balmoral. Confirmar en el lugar cuál PH específico es. Sin teléfono público.
A124: =IF(B124="","",ROW()-1) | B124: Urbanización Balmoral | C124: PH/Residencial | D124: Pedregal | E124: Av. Paseo del Mar, Urb. Balmoral, Pedregal, Panamá | J124: No | K124: Sin verificar | L124: =IF(B124="","",IF(COUNTIFS($B$2:B124,B124,$D$2:D124,D124)>1,"SI","NO")) | M124: =IF(G124="","",IF(AND(ISNUMBER(SEARCH("@",G124)),ISNUMBER(SEARCH(".",G124,SEARCH("@",G124))),LEN(G124)-LEN(SUBSTITUTE(G124,"@",""))=1,MID(G124,SEARCH("@",G124)+1,1)<>".",RIGHT(G124,1)<>"."),"Válido","Revisar")) | N124: =IF(F124="","",IF(LEN(SUBSTITUTE(SUBSTITUTE(SUBSTITUTE(SUBSTITUTE(F124,"+507",""),"-",""),"(",""),")",""))=8,"Válido","Revisar")) | O124: Urbanización completa (varios edificios/PH adentro). Sin teléfono de administración general público — verificar en persona.
A125: =IF(B125="","",ROW()-1) | B125: P.H. Mirador del Golf | C125: PH/Residencial | D125: Parque Lefevre | E125: Calle 1era, Parque Lefevre, Ciudad de Panamá | J125: No | K125: Por verificar | L125: =IF(B125="","",IF(COUNTIFS($B$2:B125,B125,$D$2:D125,D125)>1,"SI","NO")) | M125: =IF(G125="","",IF(AND(ISNUMBER(SEARCH("@",G125)),ISNUMBER(SEARCH(".",G125,SEARCH("@",G125))),LEN(G125)-LEN(SUBSTITUTE(G125,"@",""))=1,MID(G125,SEARCH("@",G125)+1,1)<>".",RIGHT(G125,1)<>"."),"Válido","Revisar")) | N125: =IF(F125="","",IF(LEN(SUBSTITUTE(SUBSTITUTE(SUBSTITUTE(SUBSTITUTE(F125,"+507",""),"-",""),"(",""),")",""))=8,"Válido","Revisar")) | O125: Torre de 12 pisos (2012), cerca de Parque Omar. Sin teléfono público listado — verificar en portería o con la administración en persona.
A126: =IF(B126="","",ROW()-1) | B126: Residencial Balmoral | C126: PH/Residencial | D126: Costa del Este | E126: Costa del Este, Panamá (dirección exacta no confirmada) | J126: No | K126: Sin verificar | L126: =IF(B126="","",IF(COUNTIFS($B$2:B126,B126,$D$2:D126,D126)>1,"SI","NO")) | M126: =IF(G126="","",IF(AND(ISNUMBER(SEARCH("@",G126)),ISNUMBER(SEARCH(".",G126,SEARCH("@",G126))),LEN(G126)-LEN(SUBSTITUTE(G126,"@",""))=1,MID(G126,SEARCH("@",G126)+1,1)<>".",RIGHT(G126,1)<>"."),"Válido","Revisar")) | N126: =IF(F126="","",IF(LEN(SUBSTITUTE(SUBSTITUTE(SUBSTITUTE(SUBSTITUTE(F126,"+507",""),"-",""),"(",""),")",""))=8,"Válido","Revisar")) | O126: Portales inmobiliarios lo listan como 'Balmoral - Costa del Este', distinto de la urbanización Balmoral en Pedregal — podría haber confusión de nombres entre ambos. Confirmar cuál es antes de visitar. Sin teléfono público.
A127: =IF(B127="","",ROW()-1) | B127: Casa Bianca | C127: PH/Residencial | D127: Costa del Este | E127: Ave. Paseo del Mar, frente a Town Center, Costa del Este, Panamá | F127: 214-2376 | G127: administracion@empresasbern.com | H127: empresasbern.com | J127: No | K127: Verificado por teléfono | L127: =IF(B127="","",IF(COUNTIFS($B$2:B127,B127,$D$2:D127,D127)>1,"SI","NO")) | M127: =IF(G127="","",IF(AND(ISNUMBER(SEARCH("@",G127)),ISNUMBER(SEARCH(".",G127,SEARCH("@",G127))),LEN(G127)-LEN(SUBSTITUTE(G127,"@",""))=1,MID(G127,SEARCH("@",G127)+1,1)<>".",RIGHT(G127,1)<>"."),"Válido","Revisar")) | N127: =IF(F127="","",IF(LEN(SUBSTITUTE(SUBSTITUTE(SUBSTITUTE(SUBSTITUTE(F127,"+507",""),"-",""),"(",""),")",""))=8,"Válido","Revisar")) | O127: Confirmado — proyecto de Empresas Bern. Teléfono y correo de administración públicos y verificados.
A128: =IF(B128="","",ROW()-1) | B128: PH Casa Bella | C128: PH/Residencial | D128: Parque Lefevre | E128: Calle María Herrera, Parque Lefevre, Panamá | J128: No | K128: Sin verificar | L128: =IF(B128="","",IF(COUNTIFS($B$2:B128,B128,$D$2:D128,D128)>1,"SI","NO")) | M128: =IF(G128="","",IF(AND(ISNUMBER(SEARCH("@",G128)),ISNUMBER(SEARCH(".",G128,SEARCH("@",G128))),LEN(G128)-LEN(SUBSTITUTE(G128,"@",""))=1,MID(G128,SEARCH("@",G128)+1,1)<>".",RIGHT(G128,1)<>"."),"Válido","Revisar")) | N128: =IF(F128="","",IF(LEN(SUBSTITUTE(SUBSTITUTE(SUBSTITUTE(SUBSTITUTE(F128,"+507",""),"-",""),"(",""),")",""))=8,"Válido","Revisar")) | O128: No se encontró registro público (web) de este PH con ese nombre y dirección — dato aportado directamente por Ani. Verificar en persona, sin fuente online que lo confirme.
A129: =IF(B129="","",ROW()-1) | B129: Casablanca | C129: PH/Residencial | D129: Santa María | E129: Santa María, Costa del Este, Panamá (dirección exacta no confirmada) | J129: No | K129: Sin verificar | L129: =IF(B129="","",IF(COUNTIFS($B$2:B129,B129,$D$2:D129,D129)>1,"SI","NO")) | M129: =IF(G129="","",IF(AND(ISNUMBER(SEARCH("@",G129)),ISNUMBER(SEARCH(".",G129,SEARCH("@",G129))),LEN(G129)-LEN(SUBSTITUTE(G129,"@",""))=1,MID(G129,SEARCH("@",G129)+1,1)<>".",RIGHT(G129,1)<>"."),"Válido","Revisar")) | N129: =IF(F129="","",IF(LEN(SUBSTITUTE(SUBSTITUTE(SUBSTITUTE(SUBSTITUTE(F129,"+507",""),"-",""),"(",""),")",""))=8,"Válido","Revisar")) | O129: No se encontró un PH residencial con ese nombre en Santa María — la búsqueda solo devolvió un restaurante y un distrito de negocios de nombre similar en Casco Viejo. Verificar en persona.
A130: =IF(B130="","",ROW()-1) | B130: Residencial Antigua | C130: PH/Residencial | D130: Costa del Este | E130: Av. Marina del Norte, Costa del Este, Panamá | J130: No | K130: Sin verificar | L130: =IF(B130="","",IF(COUNTIFS($B$2:B130,B130,$D$2:D130,D130)>1,"SI","NO")) | M130: =IF(G130="","",IF(AND(ISNUMBER(SEARCH("@",G130)),ISNUMBER(SEARCH(".",G130,SEARCH("@",G130))),LEN(G130)-LEN(SUBSTITUTE(G130,"@",""))=1,MID(G130,SEARCH("@",G130)+1,1)<>".",RIGHT(G130,1)<>"."),"Válido","Revisar")) | N130: =IF(F130="","",IF(LEN(SUBSTITUTE(SUBSTITUTE(SUBSTITUTE(SUBSTITUTE(F130,"+507",""),"-",""),"(",""),")",""))=8,"Válido","Revisar")) | O130: Desarrollo residencial exclusivo con seguridad 24/7. Solo se encontró contacto de agencias inmobiliarias que venden ahí, no de la administración del PH. Verificar en persona.
A131: =IF(B131="","",ROW()-1) | B131: Residencial Royal Pacific | C131: PH/Residencial | D131: Costa del Este | E131: Costa del Este (Juan Díaz), Panamá | J131: No | K131: Sin verificar | L131: =IF(B131="","",IF(COUNTIFS($B$2:B131,B131,$D$2:D131,D131)>1,"SI","NO")) | M131: =IF(G131="","",IF(AND(ISNUMBER(SEARCH("@",G131)),ISNUMBER(SEARCH(".",G131,SEARCH("@",G131))),LEN(G131)-LEN(SUBSTITUTE(G131,"@",""))=1,MID(G131,SEARCH("@",G131)+1,1)<>".",RIGHT(G131,1)<>"."),"Válido","Revisar")) | N131: =IF(F131="","",IF(LEN(SUBSTITUTE(SUBSTITUTE(SUBSTITUTE(SUBSTITUTE(F131,"+507",""),"-",""),"(",""),")",""))=8,"Válido","Revisar")) | O131: Ojo: existe otro 'Royal Pacific' distinto en Punta Pacífica/San Francisco (torre de 24 pisos) — no confundir. Este es el de Costa del Este/Juan Díaz. Sin teléfono de administración público, solo contacto de agencia inmobiliaria (Grupo Tribaldos).
B132: PH Terranova | C132: PH/Residencial | D132: El Cangrejo | E132: Calle Enrique Greenzier, El Cangrejo, Panamá | J132: No | K132: Sin verificar | O132: Torre de 25 pisos, construida en 2000. Sin teléfono de administración público, solo contactos de agencias inmobiliarias (Padeco Realty, Alpha Group).
A133: =IF(B133="","",ROW()-1) | B133: PH Clayton Park I | C133: PH/Residencial | D133: Clayton | E133: Clayton (Corregimiento Ancón), Panamá | J133: No | K133: Sin verificar | L133: =IF(B133="","",IF(COUNTIFS($B$2:B133,B133,$D$2:D133,D133)>1,"SI","NO")) | M133: =IF(G133="","",IF(AND(ISNUMBER(SEARCH("@",G133)),ISNUMBER(SEARCH(".",G133,SEARCH("@",G133))),LEN(G133)-LEN(SUBSTITUTE(G133,"@",""))=1,MID(G133,SEARCH("@",G133)+1,1)<>".",RIGHT(G133,1)<>"."),"Válido","Revisar")) | N133: =IF(F133="","",IF(LEN(SUBSTITUTE(SUBSTITUTE(SUBSTITUTE(SUBSTITUTE(F133,"+507",""),"-",""),"(",""),")",""))=8,"Válido","Revisar")) | O133: Comunidad residencial en Clayton. Sin teléfono de administración público — verificar en persona.
A134: =IF(B134="","",ROW()-1) | B134: PH Clayton Park II | C134: PH/Residencial | D134: Clayton | E134: Calle al Hospital, Clayton, Panamá | F134: 304-9830 / 301-0083 | H134: gproviviendan.com | J134: No | K134: Verificado por teléfono | L134: =IF(B134="","",IF(COUNTIFS($B$2:B134,B134,$D$2:D134,D134)>1,"SI","NO")) | M134: =IF(G134="","",IF(AND(ISNUMBER(SEARCH("@",G134)),ISNUMBER(SEARCH(".",G134,SEARCH("@",G134))),LEN(G134)-LEN(SUBSTITUTE(G134,"@",""))=1,MID(G134,SEARCH("@",G134)+1,1)<>".",RIGHT(G134,1)<>"."),"Válido","Revisar")) | N134: =IF(F134="","",IF(LEN(SUBSTITUTE(SUBSTITUTE(SUBSTITUTE(SUBSTITUTE(F134,"+507",""),"-",""),"(",""),")",""))=8,"Válido","Revisar")) | O134: Confirmado — desarrollo de Grupo Provivienda. 3 torres de 17 pisos. 304-9830 = oficina administrativa, 301-0083 = oficina de ventas.
A135: =IF(B135="","",ROW()-1) | B135: Clayton Tower | C135: PH/Residencial | D135: Clayton | E135: Clayton (Corregimiento Ancón), Panamá | J135: No | K135: Sin verificar | L135: =IF(B135="","",IF(COUNTIFS($B$2:B135,B135,$D$2:D135,D135)>1,"SI","NO")) | M135: =IF(G135="","",IF(AND(ISNUMBER(SEARCH("@",G135)),ISNUMBER(SEARCH(".",G135,SEARCH("@",G135))),LEN(G135)-LEN(SUBSTITUTE(G135,"@",""))=1,MID(G135,SEARCH("@",G135)+1,1)<>".",RIGHT(G135,1)<>"."),"Válido","Revisar")) | N135: =IF(F135="","",IF(LEN(SUBSTITUTE(SUBSTITUTE(SUBSTITUTE(SUBSTITUTE(F135,"+507",""),"-",""),"(",""),")",""))=8,"Válido","Revisar")) | O135: Mencionado en listados inmobiliarios de la zona, información muy escasa. Sin dirección exacta ni teléfono confirmados — verificar en persona.
A136: =IF(B136="","",ROW()-1) | B136: Clayton Village | C136: PH/Residencial | D136: Clayton | E136: Clayton (Corregimiento Ancón), Panamá | J136: No | K136: Sin verificar | L136: =IF(B136="","",IF(COUNTIFS($B$2:B136,B136,$D$2:D136,D136)>1,"SI","NO")) | M136: =IF(G136="","",IF(AND(ISNUMBER(SEARCH("@",G136)),ISNUMBER(SEARCH(".",G136,SEARCH("@",G136))),LEN(G136)-LEN(SUBSTITUTE(G136,"@",""))=1,MID(G136,SEARCH("@",G136)+1,1)<>".",RIGHT(G136,1)<>"."),"Válido","Revisar")) | N136: =IF(F136="","",IF(LEN(SUBSTITUTE(SUBSTITUTE(SUBSTITUTE(SUBSTITUTE(F136,"+507",""),"-",""),"(",""),")",""))=8,"Válido","Revisar")) | O136: Comunidad residencial cerrada con seguridad 24h. Sin teléfono de administración público — verificar en persona.
A137: =IF(B137="","",ROW()-1) | B137: Residencial Veranda | C137: PH/Residencial | D137: Costa del Este | E137: Calle R.36, Costa del Este, Panamá | J137: No | K137: Sin verificar | L137: =IF(B137="","",IF(COUNTIFS($B$2:B137,B137,$D$2:D137,D137)>1,"SI","NO")) | M137: =IF(G137="","",IF(AND(ISNUMBER(SEARCH("@",G137)),ISNUMBER(SEARCH(".",G137,SEARCH("@",G137))),LEN(G137)-LEN(SUBSTITUTE(G137,"@",""))=1,MID(G137,SEARCH("@",G137)+1,1)<>".",RIGHT(G137,1)<>"."),"Válido","Revisar")) | N137: =IF(F137="","",IF(LEN(SUBSTITUTE(SUBSTITUTE(SUBSTITUTE(SUBSTITUTE(F137,"+507",""),"-",""),"(",""),")",""))=8,"Válido","Revisar")) | O137: Confirmado como desarrollo en Costa del Este. Sin teléfono de administración público, solo agencias inmobiliarias — verificar en persona.
A138: =IF(B138="","",ROW()-1) | B138: Residencial Costa Azul | C138: PH/Residencial | D138: Costa del Este | E138: Costa del Este, Panamá | J138: No | K138: Sin verificar | L138: =IF(B138="","",IF(COUNTIFS($B$2:B138,B138,$D$2:D138,D138)>1,"SI","NO")) | M138: =IF(G138="","",IF(AND(ISNUMBER(SEARCH("@",G138)),ISNUMBER(SEARCH(".",G138,SEARCH("@",G138))),LEN(G138)-LEN(SUBSTITUTE(G138,"@",""))=1,MID(G138,SEARCH("@",G138)+1,1)<>".",RIGHT(G138,1)<>"."),"Válido","Revisar")) | N138: =IF(F138="","",IF(LEN(SUBSTITUTE(SUBSTITUTE(SUBSTITUTE(SUBSTITUTE(F138,"+507",""),"-",""),"(",""),")",""))=8,"Válido","Revisar")) | O138: Residencial con seguridad 24/7 en el corazón de Costa del Este. Sin teléfono de administración público, solo agencias inmobiliarias — verificar en persona.
A139: =IF(B139="","",ROW()-1) | L139: =IF(B139="","",IF(COUNTIFS($B$2:B139,B139,$D$2:D139,D139)>1,"SI","NO")) | M139: =IF(G139="","",IF(AND(ISNUMBER(SEARCH("@",G139)),ISNUMBER(SEARCH(".",G139,SEARCH("@",G139))),LEN(G139)-LEN(SUBSTITUTE(G139,"@",""))=1,MID(G139,SEARCH("@",G139)+1,1)<>".",RIGHT(G139,1)<>"."),"Válido","Revisar")) | N139: =IF(F139="","",IF(LEN(SUBSTITUTE(SUBSTITUTE(SUBSTITUTE(SUBSTITUTE(F139,"+507",""),"-",""),"(",""),")",""))=8,"Válido","Revisar"))
A140: =IF(B140="","",ROW()-1) | L140: =IF(B140="","",IF(COUNTIFS($B$2:B140,B140,$D$2:D140,D140)>1,"SI","NO")) | M140: =IF(G140="","",IF(AND(ISNUMBER(SEARCH("@",G140)),ISNUMBER(SEARCH(".",G140,SEARCH("@",G140))),LEN(G140)-LEN(SUBSTITUTE(G140,"@",""))=1,MID(G140,SEARCH("@",G140)+1,1)<>".",RIGHT(G140,1)<>"."),"Válido","Revisar")) | N140: =IF(F140="","",IF(LEN(SUBSTITUTE(SUBSTITUTE(SUBSTITUTE(SUBSTITUTE(F140,"+507",""),"-",""),"(",""),")",""))=8,"Válido","Revisar"))
A141: =IF(B141="","",ROW()-1) | L141: =IF(B141="","",IF(COUNTIFS($B$2:B141,B141,$D$2:D141,D141)>1,"SI","NO")) | M141: =IF(G141="","",IF(AND(ISNUMBER(SEARCH("@",G141)),ISNUMBER(SEARCH(".",G141,SEARCH("@",G141))),LEN(G141)-LEN(SUBSTITUTE(G141,"@",""))=1,MID(G141,SEARCH("@",G141)+1,1)<>".",RIGHT(G141,1)<>"."),"Válido","Revisar")) | N141: =IF(F141="","",IF(LEN(SUBSTITUTE(SUBSTITUTE(SUBSTITUTE(SUBSTITUTE(F141,"+507",""),"-",""),"(",""),")",""))=8,"Válido","Revisar"))
A142: =IF(B142="","",ROW()-1) | L142: =IF(B142="","",IF(COUNTIFS($B$2:B142,B142,$D$2:D142,D142)>1,"SI","NO")) | M142: =IF(G142="","",IF(AND(ISNUMBER(SEARCH("@",G142)),ISNUMBER(SEARCH(".",G142,SEARCH("@",G142))),LEN(G142)-LEN(SUBSTITUTE(G142,"@",""))=1,MID(G142,SEARCH("@",G142)+1,1)<>".",RIGHT(G142,1)<>"."),"Válido","Revisar")) | N142: =IF(F142="","",IF(LEN(SUBSTITUTE(SUBSTITUTE(SUBSTITUTE(SUBSTITUTE(F142,"+507",""),"-",""),"(",""),")",""))=8,"Válido","Revisar"))
A143: =IF(B143="","",ROW()-1) | L143: =IF(B143="","",IF(COUNTIFS($B$2:B143,B143,$D$2:D143,D143)>1,"SI","NO")) | M143: =IF(G143="","",IF(AND(ISNUMBER(SEARCH("@",G143)),ISNUMBER(SEARCH(".",G143,SEARCH("@",G143))),LEN(G143)-LEN(SUBSTITUTE(G143,"@",""))=1,MID(G143,SEARCH("@",G143)+1,1)<>".",RIGHT(G143,1)<>"."),"Válido","Revisar")) | N143: =IF(F143="","",IF(LEN(SUBSTITUTE(SUBSTITUTE(SUBSTITUTE(SUBSTITUTE(F143,"+507",""),"-",""),"(",""),")",""))=8,"Válido","Revisar"))
A144: =IF(B144="","",ROW()-1) | L144: =IF(B144="","",IF(COUNTIFS($B$2:B144,B144,$D$2:D144,D144)>1,"SI","NO")) | M144: =IF(G144="","",IF(AND(ISNUMBER(SEARCH("@",G144)),ISNUMBER(SEARCH(".",G144,SEARCH("@",G144))),LEN(G144)-LEN(SUBSTITUTE(G144,"@",""))=1,MID(G144,SEARCH("@",G144)+1,1)<>".",RIGHT(G144,1)<>"."),"Válido","Revisar")) | N144: =IF(F144="","",IF(LEN(SUBSTITUTE(SUBSTITUTE(SUBSTITUTE(SUBSTITUTE(F144,"+507",""),"-",""),"(",""),")",""))=8,"Válido","Revisar"))
A145: =IF(B145="","",ROW()-1) | L145: =IF(B145="","",IF(COUNTIFS($B$2:B145,B145,$D$2:D145,D145)>1,"SI","NO")) | M145: =IF(G145="","",IF(AND(ISNUMBER(SEARCH("@",G145)),ISNUMBER(SEARCH(".",G145,SEARCH("@",G145))),LEN(G145)-LEN(SUBSTITUTE(G145,"@",""))=1,MID(G145,SEARCH("@",G145)+1,1)<>".",RIGHT(G145,1)<>"."),"Válido","Revisar")) | N145: =IF(F145="","",IF(LEN(SUBSTITUTE(SUBSTITUTE(SUBSTITUTE(SUBSTITUTE(F145,"+507",""),"-",""),"(",""),")",""))=8,"Válido","Revisar"))
A146: =IF(B146="","",ROW()-1) | L146: =IF(B146="","",IF(COUNTIFS($B$2:B146,B146,$D$2:D146,D146)>1,"SI","NO")) | M146: =IF(G146="","",IF(AND(ISNUMBER(SEARCH("@",G146)),ISNUMBER(SEARCH(".",G146,SEARCH("@",G146))),LEN(G146)-LEN(SUBSTITUTE(G146,"@",""))=1,MID(G146,SEARCH("@",G146)+1,1)<>".",RIGHT(G146,1)<>"."),"Válido","Revisar")) | N146: =IF(F146="","",IF(LEN(SUBSTITUTE(SUBSTITUTE(SUBSTITUTE(SUBSTITUTE(F146,"+507",""),"-",""),"(",""),")",""))=8,"Válido","Revisar"))
A147: =IF(B147="","",ROW()-1) | L147: =IF(B147="","",IF(COUNTIFS($B$2:B147,B147,$D$2:D147,D147)>1,"SI","NO")) | M147: =IF(G147="","",IF(AND(ISNUMBER(SEARCH("@",G147)),ISNUMBER(SEARCH(".",G147,SEARCH("@",G147))),LEN(G147)-LEN(SUBSTITUTE(G147,"@",""))=1,MID(G147,SEARCH("@",G147)+1,1)<>".",RIGHT(G147,1)<>"."),"Válido","Revisar")) | N147: =IF(F147="","",IF(LEN(SUBSTITUTE(SUBSTITUTE(SUBSTITUTE(SUBSTITUTE(F147,"+507",""),"-",""),"(",""),")",""))=8,"Válido","Revisar"))
A148: =IF(B148="","",ROW()-1) | L148: =IF(B148="","",IF(COUNTIFS($B$2:B148,B148,$D$2:D148,D148)>1,"SI","NO")) | M148: =IF(G148="","",IF(AND(ISNUMBER(SEARCH("@",G148)),ISNUMBER(SEARCH(".",G148,SEARCH("@",G148))),LEN(G148)-LEN(SUBSTITUTE(G148,"@",""))=1,MID(G148,SEARCH("@",G148)+1,1)<>".",RIGHT(G148,1)<>"."),"Válido","Revisar")) | N148: =IF(F148="","",IF(LEN(SUBSTITUTE(SUBSTITUTE(SUBSTITUTE(SUBSTITUTE(F148,"+507",""),"-",""),"(",""),")",""))=8,"Válido","Revisar"))
A149: =IF(B149="","",ROW()-1) | L149: =IF(B149="","",IF(COUNTIFS($B$2:B149,B149,$D$2:D149,D149)>1,"SI","NO")) | M149: =IF(G149="","",IF(AND(ISNUMBER(SEARCH("@",G149)),ISNUMBER(SEARCH(".",G149,SEARCH("@",G149))),LEN(G149)-LEN(SUBSTITUTE(G149,"@",""))=1,MID(G149,SEARCH("@",G149)+1,1)<>".",RIGHT(G149,1)<>"."),"Válido","Revisar")) | N149: =IF(F149="","",IF(LEN(SUBSTITUTE(SUBSTITUTE(SUBSTITUTE(SUBSTITUTE(F149,"+507",""),"-",""),"(",""),")",""))=8,"Válido","Revisar"))
A150: =IF(B150="","",ROW()-1) | L150: =IF(B150="","",IF(COUNTIFS($B$2:B150,B150,$D$2:D150,D150)>1,"SI","NO")) | M150: =IF(G150="","",IF(AND(ISNUMBER(SEARCH("@",G150)),ISNUMBER(SEARCH(".",G150,SEARCH("@",G150))),LEN(G150)-LEN(SUBSTITUTE(G150,"@",""))=1,MID(G150,SEARCH("@",G150)+1,1)<>".",RIGHT(G150,1)<>"."),"Válido","Revisar")) | N150: =IF(F150="","",IF(LEN(SUBSTITUTE(SUBSTITUTE(SUBSTITUTE(SUBSTITUTE(F150,"+507",""),"-",""),"(",""),")",""))=8,"Válido","Revisar"))
... A162: =IF(B162="","",ROW()-1) | L162: =IF(B162="","",IF(COUNTIFS($B$2:B162,B162,$D$2:D162,D162)>1,"SI","NO")) | M162: =IF(G162="","",IF(AND(ISNUMBER(SEARCH("@",G162)),ISNUMBER(SEARCH(".",G162,SEARCH("@",G162))),LEN(G162)-LEN(SUBSTITUTE(G162,"@",""))=1,MID(G162,SEARCH("@",G162)+1,1)<>".",RIGHT(G162,1)<>"."),"Válido","Revisar")) | N162: =IF(F162="","",IF(LEN(SUBSTITUTE(SUBSTITUTE(SUBSTITUTE(SUBSTITUTE(F162,"+507",""),"-",""),"(",""),")",""))=8,"Válido","Revisar"))
B163: Leyenda: celdas amarillas = tú las llenas a mano. Columnas K, L, M se calculan solas. No edites la columna ID ni K/L/M. | J163: No

Sheet Resumen
A1: Resumen de Leads
A2: Se actualiza automáticamente según la pestaña 'Leads'
A4: Total de leads cargados | B4: =COUNTA(Leads!B2:B164)-1
A5: Leads duplicados detectados | B5: =COUNTIF(Leads!L2:L164,"SI")
A6: Correos con formato válido | B6: =COUNTIF(Leads!M2:M164,"Válido")
A7: Teléfonos con formato válido | B7: =COUNTIF(Leads!N2:N164,"Válido")
A8: Negocios ya visitados | B8: =COUNTIF(Leads!J2:J164,"Sí")
A10: Por zona
A11: Costa del Este | B11: =COUNTIF(Leads!D2:D131,"Costa del Este")
A12: Santa María | B12: =COUNTIF(Leads!D2:D131,"Santa María")
A13: Versalles PH1 | B13: =COUNTIF(Leads!D2:D131,"Versalles PH1")
A14: Reserva de Versalles | B14: =COUNTIF(Leads!D2:D131,"Reserva de Versalles")
A15: Versalles PH2 | B15: =COUNTIF(Leads!D2:D131,"Versalles PH2")
A16: Don Bosco | B16: =COUNTIF(Leads!D2:D131,"Don Bosco")
A17: Vía Brasil | B17: =COUNTIF(Leads!D2:D131,"Vía Brasil")
A18: Avenida Balboa / Cinta Costera | B18: =COUNTIF(Leads!D2:D131,"Avenida Balboa / Cinta Costera")
A19: Otra zona Ciudad de Panamá | B19: =COUNTIF(Leads!D2:D131,"Otra zona Ciudad de Panamá")
A21: Por tipo de negocio
A22: Hotel | B22: =COUNTIF(Leads!C2:C131,"Hotel")
A23: PH/Residencial | B23: =COUNTIF(Leads!C2:C131,"PH/Residencial")
A24: Oficina | B24: =COUNTIF(Leads!C2:C131,"Oficina")
A25: Clínica | B25: =COUNTIF(Leads!C2:C131,"Clínica")
A26: Negocio general | B26: =COUNTIF(Leads!C2:C131,"Negocio general")
A27: Otro | B27: =COUNTIF(Leads!C2:C131,"Otro")

Sheet VISITADOS
A1: Negocios visitados
A2: Esta lista se llena sola con los negocios marcados como 'Sí' en la columna Visita AC de la pestaña Leads.
A4: Negocio | B4: Tipo | C4: Zona | D4: Teléfono | E4: Correo | F4: Notas
A5: =IFERROR(FILTER(Leads!B2:B134, Leads!J2:J134="Sí"), "") | B5: =IFERROR(FILTER(Leads!C2:C134, Leads!J2:J134="Sí"), "") | C5: =IFERROR(FILTER(Leads!D2:D134, Leads!J2:J134="Sí"), "") | D5: =IFERROR(FILTER(Leads!F2:F134, Leads!J2:J134="Sí"), "") | E5: =IFERROR(FILTER(Leads!G2:G134, Leads!J2:J134="Sí"), "") | F5: =IFERROR(FILTER(Leads!O2:O134, Leads!J2:J134="Sí"), "")
A50: Nota: si ves el error #¡NOMBRE? en vez de la lista, tu versión de Excel no soporta la función FILTER (necesitas Excel 365 o 2021+).
A51: En ese caso: ve a la pestaña 'Leads', activa el Filtro automático en el encabezado, y filtra la columna 'Visita AC' = Sí.
